Workbook

Sheet Dashboard
A1: MARKET MACHINE DASHBOARD v4.6 — FINAL CALIBRATED LIVING ENGINE | K1: LIVE PIPE STATUS
A2: Live evidence engine + calibrated hourly timing/seasonality: FRED + CFTC/TFF + TradingView → Signal Engine → Machine score → calendar timing → final read | K2: Pipe | L2: Source | M2: Status | N2: Latest Value | O2: Last Update | P2: Mode | Q2: Notes | R2: Action
K3: DXY / Price Structure | L3: TradingView Webhook | M3: {=IFERROR(INDEX(Live_Inputs!$D$2:$D$20,MATCH($B$4&"|DXY",Live_Inputs!$A$2:$A$20&"|"&Live_Inputs!$B$2:$B$20,0)),"Manual")} -> Bearish | N3: {=IFERROR(INDEX(Live_Inputs!$E$2:$E$20,MATCH($B$4&"|DXY",Live_Inputs!$A$2:$A$20&"|"&Live_Inputs!$B$2:$B$20,0)),"—")} -> Manual | O3: {=IFERROR(INDEX(Live_Inputs!$F$2:$F$20,MATCH($B$4&"|DXY",Live_Inputs!$A$2:$A$20&"|"&Live_Inputs!$B$2:$B$20,0)),"—")} -> Manual | P3: Live / Manual | Q3: Webhook alert updates this row when configured. | R3: TradingView alert → Apps Script
A4: Selected Asset | B4: XAGUSD | K4: Real Yields | L4: FRED DFII10 | M4: =IF(Live_Inputs!$D$3<>"",Live_Inputs!$D$3,"Manual") -> Bearish | N4: =IF(Live_Inputs!$E$3<>"",Live_Inputs!$E$3,"—") -> 2.11 | O4: =IF(Live_Inputs!$F$3<>"",Live_Inputs!$F$3,"—") -> 46180.553 | P4: Auto | Q4: FRED 10-year TIPS real yield. | R4: Run refreshFRED()
K5: Managed Money | L5: CFTC COT | M5: {=IFERROR(INDEX(Live_Inputs!$D$2:$D$20,MATCH($B$4&"|Managed Money",Live_Inputs!$A$2:$A$20&"|"&Live_Inputs!$B$2:$B$20,0)),"Manual")} -> Bullish | N5: {=IFERROR(INDEX(Live_Inputs!$E$2:$E$20,MATCH($B$4&"|Managed Money",Live_Inputs!$A$2:$A$20&"|"&Live_Inputs!$B$2:$B$20,0)),"—")} -> 23926 | O5: {=IFERROR(INDEX(Live_Inputs!$F$2:$F$20,MATCH($B$4&"|Managed Money",Live_Inputs!$A$2:$A$20&"|"&Live_Inputs!$B$2:$B$20,0)),"—")} -> 46175 | P5: Weekly Auto / Manual | Q5: CFTC updates weekly after Friday release. | R5: Run refreshCFTC()
A6: MACHINE SCORE | K6: Open Interest | L6: CFTC / Exchange / Manual | M6: {=IFERROR(INDEX(Live_Inputs!$D$2:$D$20,MATCH($B$4&"|Open Interest",Live_Inputs!$A$2:$A$20&"|"&Live_Inputs!$B$2:$B$20,0)),"Manual")} -> Bullish | N6: {=IFERROR(INDEX(Live_Inputs!$E$2:$E$20,MATCH($B$4&"|Open Interest",Live_Inputs!$A$2:$A$20&"|"&Live_Inputs!$B$2:$B$20,0)),"—")} -> 102809 | O6: {=IFERROR(INDEX(Live_Inputs!$F$2:$F$20,MATCH($B$4&"|Open Interest",Live_Inputs!$A$2:$A$20&"|"&Live_Inputs!$B$2:$B$20,0)),"—")} -> 46175 | P6: Weekly Auto / Manual | Q6: OI from CFTC report or exchange feed. | R6: Run refreshCFTC()
A7: Variable | B7: Status | C7: Weight | D7: Bullish | E7: Bearish | F7: Neutral | G7: Machine Impact | H7: Notes
A8: DXY | B8: {=IFERROR(XLOOKUP($B$4,Signal_Engine!$A:$A,Signal_Engine!$U:$U),"Neutral")} -> Neutral | C8: {=INDEX(Machine_Input!$G$2:$G$51,MATCH($B$4,Machine_Input!$B$2:$B$51,0))} -> 0.3 | D8: =IF($B8="Bullish","✓","") | E8: =IF($B8="Bearish","✓","") | F8: =IF($B8="Neutral","✓","") -> ✓ | G8: Dollar pressure / relief | H8: Auto from Signal_Engine | K8: V4.6 CALIBRATION NOTE
A9: Real Yields | B9: {=IFERROR(XLOOKUP($B$4,Signal_Engine!$A:$A,Signal_Engine!$Q:$Q),"Neutral")} -> Neutral | C9: {=INDEX(Machine_Input!$H$2:$H$51,MATCH($B$4,Machine_Input!$B$2:$B$51,0))} -> 0.3 | D9: =IF($B9="Bullish","✓","") | E9: =IF($B9="Bearish","✓","") | F9: =IF($B9="Neutral","✓","") -> ✓ | G9: Discount-rate pressure | H9: Auto from Signal_Engine | K9: Timing and seasonality layers now use uploaded hourly datasets for XAGUSD, US30, SPX500, NAS100, plus cross-checks from SI, DJI, VIX, GOLD, and NDX.
A10: Managed Money | B10: {=IFERROR(XLOOKUP($B$4,Signal_Engine!$A:$A,Signal_Engine!$R:$R),"Neutral")} -> Bullish | C10: {=INDEX(Machine_Input!$I$2:$I$51,MATCH($B$4,Machine_Input!$B$2:$B$51,0))} -> 0.25 | D10: =IF($B10="Bullish","✓","") -> ✓ | E10: =IF($B10="Bearish","✓","") | F10: =IF($B10="Neutral","✓","") | G10: Institutional positioning | H10: Auto from Signal_Engine | K10: CFTC script now stages asset-coded proxy rows so Signal_Engine can read XAGUSD/US30/SPX500/NAS100 consistently after refreshCFTC().
A11: Open Interest | B11: {=IFERROR(XLOOKUP($B$4,Signal_Engine!$A:$A,Signal_Engine!$T:$T),"Neutral")} -> Neutral | C11: {=INDEX(Machine_Input!$J$2:$J$51,MATCH($B$4,Machine_Input!$B$2:$B$51,0))} -> 0.15 | D11: =IF($B11="Bullish","✓","") | E11: =IF($B11="Bearish","✓","") | F11: =IF($B11="Neutral","✓","") -> ✓ | G11: Participation / conviction | H11: Auto from Signal_Engine | K11: Next calibration step: run refreshFRED(), refreshCFTC(), then verify Signal_Engine rows update and Dashboard timing layer changes with selected asset. | L11: Living machine-ready after scripts are installed and refreshed.
A13: Bullish Count | B13: {=IFERROR(XLOOKUP($B$4,Signal_Engine!$A:$A,Signal_Engine!$V:$V),0)} -> 1 | C13: Bearish Count | D13: {=IFERROR(XLOOKUP($B$4,Signal_Engine!$A:$A,Signal_Engine!$W:$W),0)} -> 0 | E13: Neutral Count | F13: {=IFERROR(XLOOKUP($B$4,Signal_Engine!$A:$A,Signal_Engine!$X:$X),0)} -> 3 | K13: FINAL WEIGHTED MACHINE
A14: Bullish % | B14: {=IFERROR(XLOOKUP($B$4,Signal_Engine!$A:$A,Signal_Engine!$AQ:$AQ),0)} -> 0.064516129 | C14: Bearish % | D14: {=IFERROR(XLOOKUP($B$4,Signal_Engine!$A:$A,Signal_Engine!$AR:$AR),0)} -> 0.064516129 | E14: Neutral % | F14: {=IFERROR(XLOOKUP($B$4,Signal_Engine!$A:$A,Signal_Engine!$AS:$AS),0)} -> 0.87096774 | K14: Bullish Points | L14: {=IFERROR(XLOOKUP($B$4,Signal_Engine!$A:$A,Signal_Engine!$AN:$AN),0)} -> 10 | M14: Bearish Points | N14: {=IFERROR(XLOOKUP($B$4,Signal_Engine!$A:$A,Signal_Engine!$AO:$AO),0)} -> 10
A15: Machine Bias | B15: {=IFERROR(XLOOKUP($B$4,Signal_Engine!$A:$A,Signal_Engine!$AT:$AT),"Neutral / Mixed")} -> Neutral / Mixed | C15: Evidence Text | D15: {=IFERROR(XLOOKUP($B$4,Signal_Engine!$A:$A,Signal_Engine!$AU:$AU),"")} -> Pts → Bull 10 | Bear 10 | Neutral 135 || Commercial -1,768 (-10) | NonComm 2,406 (10) | OI -17,080 (0) | DXY Neutral (0) | RealYield Neutral (0) | E15: Interpretation | F15: {=IF(B15="Strong Bearish","High-conviction bearish machine pressure.",IF(B15="Strong Bullish","High-conviction bullish machine pressure.",IF(B15="Bearish","Bearish machine pressure outweighs bullish evidence.",IF(B15="Bullish","Bullish machine pressure outweighs bearish evidence.",IF(B15="Moderate Bearish","Moderate bearish skew; confirm with structure/timing.",IF(B15="Moderate Bullish","Moderate bullish skew; confirm with structure/timing.","Mixed machine; wait for cleaner alignment."))))))} -> Mixed machine; wait for cleaner alignment. | K15: Neutral Points | L15: {=IFERROR(XLOOKUP($B$4,Signal_Engine!$A:$A,Signal_Engine!$AP:$AP),0)} -> 135 | M15: Conviction | N15: =MAX(L14,N14)/155 -> 0.064516129
K16: Machine Reading | L16: =B15 -> Neutral / Mixed
A17: SEASONAL LAYER | K17: Score Notes | L17: =D15 -> Pts → Bull 10 | Bear 10 | Neutral 135 || Commercial -1,768 (-10) | NonComm 2,406 (10) | OI -17,080 (0) | DXY Neutral (0) | RealYield Neutral (0)
A18: Current Month | B18: Seasonal Bias | C18: Strength | D18: Calendar Note | E18: Conflict / Confirmation | F18: Source | G18: Update Sheet
A19: =TEXT(TODAY(),"mmmm") -> June | B19: {=IFERROR(INDEX(Seasonality!$D$2:$D$200,MATCH(1,(Seasonality!$A$2:$A$200=$B$4)*(Seasonality!$B$2:$B$200=A19),0)),"Neutral")} -> Bearish | C19: {=IFERROR(INDEX(Seasonality!$E$2:$E$200,MATCH(1,(Seasonality!$A$2:$A$200=$B$4)*(Seasonality!$B$2:$B$200=A19),0)),"Weak")} -> Strong | D19: {=IFERROR(INDEX(Seasonality!$F$2:$F$200,MATCH(1,(Seasonality!$A$2:$A$200=$B$4)*(Seasonality!$B$2:$B$200=A19),0)),"Add seasonal stats")} -> Samples 4 | Win 25.0% | Avg range 11.7% | E19: =IF(AND(B19="Bullish",OR($B$15="Bearish",$B$15="Strong Bearish",$B$15="Moderate Bearish")),"Conflict: bullish seasonality vs bearish machine",IF(AND(B19="Bearish",OR($B$15="Bullish",$B$15="Strong Bullish",$B$15="Moderate Bullish")),"Conflict: bearish seasonality vs bullish machine","Aligned / Neutral")) -> Aligned / Neutral | F19: Seasonality | G19: Seasonality
A22: TIMING LAYER
A23: Machine State Used | B23: Weekly High Window | C23: Weekly Low Window | D23: Primary Hour | E23: Timing Note | F23: Confidence | G23: Source | H23: Update Sheet
A24: =IF(OR($B$15="Strong Bearish",$B$15="Bearish",$B$15="Moderate Bearish"),"Bearish",IF(OR($B$15="Strong Bullish",$B$15="Bullish",$B$15="Moderate Bullish"),"Bullish","Neutral")) -> Neutral | B24: {=IFERROR(INDEX(Timing!$C$2:$C$100,MATCH(1,(Timing!$A$2:$A$100=$B$4)*(Timing!$B$2:$B$100=$A24),0)),"To refine")} -> Friday (35.8%) | Sun–Tue high 35.8% | C24: {=IFERROR(INDEX(Timing!$D$2:$D$100,MATCH(1,(Timing!$A$2:$A$100=$B$4)*(Timing!$B$2:$B$100=$A24),0)),"To refine")} -> Sunday (20.7%) | Sun–Tue low 52.5% | D24: {=IFERROR(INDEX(Timing!$E$2:$E$100,MATCH(1,(Timing!$A$2:$A$100=$B$4)*(Timing!$B$2:$B$100=$A24),0)),"To refine")} -> High 09:00 ET (15.1%) / Low 18:00 ET (18.4%) | E24: {=IFERROR(INDEX(Timing!$G$2:$G$100,MATCH(1,(Timing!$A$2:$A$100=$B$4)*(Timing!$B$2:$B$100=$A24),0)),"To refine")} -> Baseline mixed-machine timing. Use as reference only; high-before-low 44.7%. | F24: {=IFERROR(INDEX(Timing!$H$2:$H$100,MATCH(1,(Timing!$A$2:$A$100=$B$4)*(Timing!$B$2:$B$100=$A24),0)),"To refine")} -> High | G24: {=IFERROR(INDEX(Timing!$J$2:$J$100,MATCH(1,(Timing!$A$2:$A$100=$B$4)*(Timing!$B$2:$B$100=$A24),0)),"To refine")} -> Hourly calibration dataset | H24: Timing
A27: STRUCTURE LAYER
A28: Current Price | B28: Key Level | C28: Structure Status | D28: Acceptance | E28: Structure Score | F28: Note | G28: Last Updated | H28: Update Sheet
A29: {=IFERROR(INDEX(Structure!$B$2:$B$100,MATCH($B$4,Structure!$A$2:$A$100,0)),"Manual")} -> Manual | B29: {=IFERROR(INDEX(Structure!$C$2:$C$100,MATCH($B$4,Structure!$A$2:$A$100,0)),"Manual")} -> 68 / manual | C29: {=IFERROR(INDEX(Structure!$D$2:$D$100,MATCH($B$4,Structure!$A$2:$A$100,0)),"Manual")} -> Below key level | D29: {=IFERROR(INDEX(Structure!$E$2:$E$100,MATCH($B$4,Structure!$A$2:$A$100,0)),"Manual")} -> Pending confirmation | E29: {=IFERROR(INDEX(Structure!$F$2:$F$100,MATCH($B$4,Structure!$A$2:$A$100,0)),"Manual")} -> -1 | F29: {=IFERROR(INDEX(Structure!$G$2:$G$100,MATCH($B$4,Structure!$A$2:$A$100,0)),"Manual")} -> Update manually based on weekly close / acceptance | G29: {=IFERROR(INDEX(Structure!$H$2:$H$100,MATCH($B$4,Structure!$A$2:$A$100,0)),"Manual")} -> Manual | H29: Structure
A32: SIGNAL ENGINE SNAPSHOT
A33: Asset | B33: Commercial Δ | C33: Noncommercial Δ | D33: OI Δ | E33: Real Yield Δ | F33: DXY Signal | G33: Machine Bias | H33: Notes | I33: Next Check
A34: =$B$4 -> XAGUSD | B34: {=IFERROR(XLOOKUP($B$4,Signal_Engine!$A:$A,Signal_Engine!$J:$J),0)} -> -1768 | C34: {=IFERROR(XLOOKUP($B$4,Signal_Engine!$A:$A,Signal_Engine!$M:$M),0)} -> 2406 | D34: {=IFERROR(XLOOKUP($B$4,Signal_Engine!$A:$A,Signal_Engine!$G:$G),0)} -> -17080 | E34: {=IFERROR(XLOOKUP($B$4,Signal_Engine!$A:$A,Signal_Engine!$P:$P),0)} -> 0 | F34: {=IFERROR(XLOOKUP($B$4,Signal_Engine!$A:$A,Signal_Engine!$U:$U),"Neutral")} -> Neutral | G34: {=IFERROR(XLOOKUP($B$4,Signal_Engine!$A:$A,Signal_Engine!$AT:$AT),"Neutral / Mixed")} -> Neutral / Mixed | H34: {=IFERROR(XLOOKUP($B$4,Signal_Engine!$A:$A,Signal_Engine!$AU:$AU),"")} -> Pts → Bull 10 | Bear 10 | Neutral 135 || Commercial -1,768 (-10) | NonComm 2,406 (10) | OI -17,080 (0) | DXY Neutral (0) | RealYield Neutral (0) | I34: {=IFERROR(XLOOKUP($B$4,Signal_Engine!$A:$A,Signal_Engine!$AE:$AE),"")} -> 46182.829
A35: ="FINAL READ: "&$B$4&" | Machine: "&B15&" | Bullish "&TEXT(B14,"0%")&" / Bearish "&TEXT(D14,"0%")&" / Neutral "&TEXT(F14,"0%")&" | Evidence: "&D15&" | Seasonality: "&B19&" / "&C19&" | Timing: "&B24&" → "&E24&" | Structure: "&C29&" / "&D29 -> FINAL READ: XAGUSD | Machine: Neutral / Mixed | Bullish 6% / Bearish 6% / Neutral 87% | Evidence: Pts → Bull 10 | Bear 10 | Neutral 135 || Commercial -1,768 (-10) | NonComm 2,406 (10) | OI -17,080 (0) | DXY Neutral (0) | RealYield Neutral (0) | Seasonality: Bearish / Strong | Timing: Friday (35.8%) | Sun–Tue high 35.8% → Baseline mixed-machine timing. Use as reference only; high-before-low 44.7%. | Structure: Below key level / Pending confirmation

Sheet Machine_Input
A1: Date | B1: Asset | C1: DXY Status | D1: Real Yields Status | E1: Managed Money / Positioning | F1: Open Interest | G1: DXY Weight | H1: Real Yield Weight | I1: Managed Money Weight | J1: OI Weight | K1: Bullish Count | L1: Bearish Count | M1: Neutral Count | N1: Final Bullish % | O1: Final Bearish % | P1: Final Neutral % | Q1: Machine Bias | R1: Evidence Text | S1: Interpretation | T1: Data Mode | U1: DXY Live Status | V1: Real Yield Live Status | W1: MM Live Status | X1: OI Live Status | Y1: Live Freshness | Z1: Live Override? | AA1: Notes
A2: {=IFERROR(INDEX(Signal_Engine!$AE:$AE,MATCH($B2,Signal_Engine!$A:$A,0)),NOW())} -> 46182.829 | B2: XAGUSD | C2: {=IFERROR(XLOOKUP($B2,Signal_Engine!$A:$A,Signal_Engine!$U:$U),"Neutral")} -> Neutral | D2: {=IFERROR(XLOOKUP($B2,Signal_Engine!$A:$A,Signal_Engine!$Q:$Q),"Neutral")} -> Neutral | E2: {=IFERROR(XLOOKUP($B2,Signal_Engine!$A:$A,Signal_Engine!$R:$R),"Neutral")} -> Bullish | F2: {=IFERROR(XLOOKUP($B2,Signal_Engine!$A:$A,Signal_Engine!$T:$T),"Neutral")} -> Neutral | G2: 0.3 | H2: 0.3 | I2: 0.25 | J2: 0.15 | K2: {=IFERROR(INDEX(Signal_Engine!$V:$V,MATCH($B2,Signal_Engine!$A:$A,0)),0)} -> 1 | L2: {=IFERROR(INDEX(Signal_Engine!$W:$W,MATCH($B2,Signal_Engine!$A:$A,0)),0)} -> 0 | M2: {=IFERROR(INDEX(Signal_Engine!$X:$X,MATCH($B2,Signal_Engine!$A:$A,0)),0)} -> 3 | N2: {=IFERROR(XLOOKUP($B2,Signal_Engine!$A:$A,Signal_Engine!$AQ:$AQ),0)} -> 0.064516129 | O2: {=IFERROR(XLOOKUP($B2,Signal_Engine!$A:$A,Signal_Engine!$AR:$AR),0)} -> 0.064516129 | P2: {=IFERROR(XLOOKUP($B2,Signal_Engine!$A:$A,Signal_Engine!$AS:$AS),1)} -> 0.87096774 | Q2: {=IFERROR(XLOOKUP($B2,Signal_Engine!$A:$A,Signal_Engine!$AT:$AT),"Neutral / Mixed")} -> Neutral / Mixed | R2: {=IFERROR(XLOOKUP($B2,Signal_Engine!$A:$A,Signal_Engine!$AU:$AU),"")} -> Pts → Bull 10 | Bear 10 | Neutral 135 || Commercial -1,768 (-10) | NonComm 2,406 (10) | OI -17,080 (0) | DXY Neutral (0) | RealYield Neutral (0) | S2: {=IF(Q2="Strong Bearish","High-conviction bearish machine pressure.",IF(Q2="Strong Bullish","High-conviction bullish machine pressure.",IF(Q2="Bearish","Bearish machine pressure outweighs bullish evidence.",IF(Q2="Bullish","Bullish machine pressure outweighs bearish evidence.",IF(Q2="Moderate Bearish","Moderate bearish skew; confirm with structure/timing.",IF(Q2="Moderate Bullish","Moderate bullish skew; confirm with structure/timing.","Mixed machine; wait for cleaner alignment."))))))} -> Mixed machine; wait for cleaner alignment. | T2: =IF(Z2="Yes","Live","Manual") -> Live | U2: {=C2} -> Neutral | V2: {=D2} -> Neutral | W2: {=E2} -> Bullish | X2: {=F2} -> Neutral | Y2: =A2 -> 46182.829 | Z2: Yes | AA2: {=IFERROR(INDEX(Signal_Engine!$AF:$AF,MATCH($B2,Signal_Engine!$A:$A,0)),"Auto-connected to Signal_Engine.")} -> RealYield Δ 0.00 | NonComm Δ 2,406 | Commercial Δ -1,768 | OI Δ -17,080
A3: {=IFERROR(INDEX(Signal_Engine!$AE:$AE,MATCH($B3,Signal_Engine!$A:$A,0)),NOW())} -> 46182.829 | B3: US30 | C3: {=IFERROR(XLOOKUP($B3,Signal_Engine!$A:$A,Signal_Engine!$U:$U),"Neutral")} -> Neutral | D3: {=IFERROR(XLOOKUP($B3,Signal_Engine!$A:$A,Signal_Engine!$Q:$Q),"Neutral")} -> Neutral | E3: {=IFERROR(XLOOKUP($B3,Signal_Engine!$A:$A,Signal_Engine!$R:$R),"Neutral")} -> Bullish | F3: {=IFERROR(XLOOKUP($B3,Signal_Engine!$A:$A,Signal_Engine!$T:$T),"Neutral")} -> Neutral | G3: 0.3 | H3: 0.3 | I3: 0.25 | J3: 0.15 | K3: {=IFERROR(INDEX(Signal_Engine!$V:$V,MATCH($B3,Signal_Engine!$A:$A,0)),0)} -> 1 | L3: {=IFERROR(INDEX(Signal_Engine!$W:$W,MATCH($B3,Signal_Engine!$A:$A,0)),0)} -> 0 | M3: {=IFERROR(INDEX(Signal_Engine!$X:$X,MATCH($B3,Signal_Engine!$A:$A,0)),0)} -> 3 | N3: {=IFERROR(XLOOKUP($B3,Signal_Engine!$A:$A,Signal_Engine!$AQ:$AQ),0)} -> 0.064516129 | O3: {=IFERROR(XLOOKUP($B3,Signal_Engine!$A:$A,Signal_Engine!$AR:$AR),0)} -> 0.064516129 | P3: {=IFERROR(XLOOKUP($B3,Signal_Engine!$A:$A,Signal_Engine!$AS:$AS),1)} -> 0.87096774 | Q3: {=IFERROR(XLOOKUP($B3,Signal_Engine!$A:$A,Signal_Engine!$AT:$AT),"Neutral / Mixed")} -> Neutral / Mixed | R3: {=IFERROR(XLOOKUP($B3,Signal_Engine!$A:$A,Signal_Engine!$AU:$AU),"")} -> Pts → Bull 10 | Bear 10 | Neutral 135 || Commercial -1,198 (-10) | NonComm 1,939 (10) | OI -1,455 (0) | DXY Neutral (0) | RealYield Neutral (0) | S3: {=IF(Q3="Strong Bearish","High-conviction bearish machine pressure.",IF(Q3="Strong Bullish","High-conviction bullish machine pressure.",IF(Q3="Bearish","Bearish machine pressure outweighs bullish evidence.",IF(Q3="Bullish","Bullish machine pressure outweighs bearish evidence.",IF(Q3="Moderate Bearish","Moderate bearish skew; confirm with structure/timing.",IF(Q3="Moderate Bullish","Moderate bullish skew; confirm with structure/timing.","Mixed machine; wait for cleaner alignment."))))))} -> Mixed machine; wait for cleaner alignment. | T3: =IF(Z3="Yes","Live","Manual") -> Live | U3: {=C3} -> Neutral | V3: {=D3} -> Neutral | W3: {=E3} -> Bullish | X3: {=F3} -> Neutral | Y3: =A3 -> 46182.829 | Z3: Yes | AA3: {=IFERROR(INDEX(Signal_Engine!$AF:$AF,MATCH($B3,Signal_Engine!$A:$A,0)),"Auto-connected to Signal_Engine.")} -> RealYield Δ 0.00 | NonComm Δ 1,939 | Commercial Δ -1,198 | OI Δ -1,455
A4: {=IFERROR(INDEX(Signal_Engine!$AE:$AE,MATCH($B4,Signal_Engine!$A:$A,0)),NOW())} -> 46182.829 | B4: SPX500 | C4: {=IFERROR(XLOOKUP($B4,Signal_Engine!$A:$A,Signal_Engine!$U:$U),"Neutral")} -> Neutral | D4: {=IFERROR(XLOOKUP($B4,Signal_Engine!$A:$A,Signal_Engine!$Q:$Q),"Neutral")} -> Neutral | E4: {=IFERROR(XLOOKUP($B4,Signal_Engine!$A:$A,Signal_Engine!$R:$R),"Neutral")} -> Bearish | F4: {=IFERROR(XLOOKUP($B4,Signal_Engine!$A:$A,Signal_Engine!$T:$T),"Neutral")} -> Neutral | G4: 0.3 | H4: 0.3 | I4: 0.25 | J4: 0.15 | K4: {=IFERROR(INDEX(Signal_Engine!$V:$V,MATCH($B4,Signal_Engine!$A:$A,0)),0)} -> 0 | L4: {=IFERROR(INDEX(Signal_Engine!$W:$W,MATCH($B4,Signal_Engine!$A:$A,0)),0)} -> 1 | M4: {=IFERROR(INDEX(Signal_Engine!$X:$X,MATCH($B4,Signal_Engine!$A:$A,0)),0)} -> 3 | N4: {=IFERROR(XLOOKUP($B4,Signal_Engine!$A:$A,Signal_Engine!$AQ:$AQ),0)} -> 0.25806452 | O4: {=IFERROR(XLOOKUP($B4,Signal_Engine!$A:$A,Signal_Engine!$AR:$AR),0)} -> 0.25806452 | P4: {=IFERROR(XLOOKUP($B4,Signal_Engine!$A:$A,Signal_Engine!$AS:$AS),1)} -> 0.48387097 | Q4: {=IFERROR(XLOOKUP($B4,Signal_Engine!$A:$A,Signal_Engine!$AT:$AT),"Neutral / Mixed")} -> Neutral / Mixed | R4: {=IFERROR(XLOOKUP($B4,Signal_Engine!$A:$A,Signal_Engine!$AU:$AU),"")} -> Pts → Bull 40 | Bear 40 | Neutral 75 || Commercial 55,145 (40) | NonComm -54,937 (-40) | OI 55,610 (0) | DXY Neutral (0) | RealYield Neutral (0) | S4: {=IF(Q4="Strong Bearish","High-conviction bearish machine pressure.",IF(Q4="Strong Bullish","High-conviction bullish machine pressure.",IF(Q4="Bearish","Bearish machine pressure outweighs bullish evidence.",IF(Q4="Bullish","Bullish machine pressure outweighs bearish evidence.",IF(Q4="Moderate Bearish","Moderate bearish skew; confirm with structure/timing.",IF(Q4="Moderate Bullish","Moderate bullish skew; confirm with structure/timing.","Mixed machine; wait for cleaner alignment."))))))} -> Mixed machine; wait for cleaner alignment. | T4: =IF(Z4="Yes","Live","Manual") -> Live | U4: {=C4} -> Neutral | V4: {=D4} -> Neutral | W4: {=E4} -> Bearish | X4: {=F4} -> Neutral | Y4: =A4 -> 46182.829 | Z4: Yes | AA4: {=IFERROR(INDEX(Signal_Engine!$AF:$AF,MATCH($B4,Signal_Engine!$A:$A,0)),"Auto-connected to Signal_Engine.")} -> RealYield Δ 0.00 | NonComm Δ -54,937 | Commercial Δ 55,145 | OI Δ 55,610
A5: {=IFERROR(INDEX(Signal_Engine!$AE:$AE,MATCH($B5,Signal_Engine!$A:$A,0)),NOW())} -> 46182.829 | B5: NAS100 | C5: {=IFERROR(XLOOKUP($B5,Signal_Engine!$A:$A,Signal_Engine!$U:$U),"Neutral")} -> Neutral | D5: {=IFERROR(XLOOKUP($B5,Signal_Engine!$A:$A,Signal_Engine!$Q:$Q),"Neutral")} -> Neutral | E5: {=IFERROR(XLOOKUP($B5,Signal_Engine!$A:$A,Signal_Engine!$R:$R),"Neutral")} -> Bearish | F5: {=IFERROR(XLOOKUP($B5,Signal_Engine!$A:$A,Signal_Engine!$T:$T),"Neutral")} -> Neutral | G5: 0.3 | H5: 0.3 | I5: 0.25 | J5: 0.15 | K5: {=IFERROR(INDEX(Signal_Engine!$V:$V,MATCH($B5,Signal_Engine!$A:$A,0)),0)} -> 0 | L5: {=IFERROR(INDEX(Signal_Engine!$W:$W,MATCH($B5,Signal_Engine!$A:$A,0)),0)} -> 1 | M5: {=IFERROR(INDEX(Signal_Engine!$X:$X,MATCH($B5,Signal_Engine!$A:$A,0)),0)} -> 3 | N5: {=IFERROR(XLOOKUP($B5,Signal_Engine!$A:$A,Signal_Engine!$AQ:$AQ),0)} -> 0.25806452 | O5: {=IFERROR(XLOOKUP($B5,Signal_Engine!$A:$A,Signal_Engine!$AR:$AR),0)} -> 0.25806452 | P5: {=IFERROR(XLOOKUP($B5,Signal_Engine!$A:$A,Signal_Engine!$AS:$AS),1)} -> 0.48387097 | Q5: {=IFERROR(XLOOKUP($B5,Signal_Engine!$A:$A,Signal_Engine!$AT:$AT),"Neutral / Mixed")} -> Neutral / Mixed | R5: {=IFERROR(XLOOKUP($B5,Signal_Engine!$A:$A,Signal_Engine!$AU:$AU),"")} -> Pts → Bull 40 | Bear 40 | Neutral 75 || Commercial 15,302 (40) | NonComm -10,803 (-40) | OI 15,220 (0) | DXY Neutral (0) | RealYield Neutral (0) | S5: {=IF(Q5="Strong Bearish","High-conviction bearish machine pressure.",IF(Q5="Strong Bullish","High-conviction bullish machine pressure.",IF(Q5="Bearish","Bearish machine pressure outweighs bullish evidence.",IF(Q5="Bullish","Bullish machine pressure outweighs bearish evidence.",IF(Q5="Moderate Bearish","Moderate bearish skew; confirm with structure/timing.",IF(Q5="Moderate Bullish","Moderate bullish skew; confirm with structure/timing.","Mixed machine; wait for cleaner alignment."))))))} -> Mixed machine; wait for cleaner alignment. | T5: =IF(Z5="Yes","Live","Manual") -> Live | U5: {=C5} -> Neutral | V5: {=D5} -> Neutral | W5: {=E5} -> Bearish | X5: {=F5} -> Neutral | Y5: =A5 -> 46182.829 | Z5: Yes | AA5: {=IFERROR(INDEX(Signal_Engine!$AF:$AF,MATCH($B5,Signal_Engine!$A:$A,0)),"Auto-connected to Signal_Engine.")} -> RealYield Δ 0.00 | NonComm Δ -10,803 | Commercial Δ 15,302 | OI Δ 15,220
A6: {=IFERROR(INDEX(Signal_Engine!$AE:$AE,MATCH($B6,Signal_Engine!$A:$A,0)),NOW())} -> 46182.829 | B6: Custom | C6: {=IFERROR(XLOOKUP($B6,Signal_Engine!$A:$A,Signal_Engine!$U:$U),"Neutral")} -> Neutral | D6: {=IFERROR(XLOOKUP($B6,Signal_Engine!$A:$A,Signal_Engine!$Q:$Q),"Neutral")} -> Neutral | E6: {=IFERROR(XLOOKUP($B6,Signal_Engine!$A:$A,Signal_Engine!$R:$R),"Neutral")} -> Neutral | F6: {=IFERROR(XLOOKUP($B6,Signal_Engine!$A:$A,Signal_Engine!$T:$T),"Neutral")} -> Neutral | G6: 0.3 | H6: 0.3 | I6: 0.25 | J6: 0.15 | K6: {=IFERROR(INDEX(Signal_Engine!$V:$V,MATCH($B6,Signal_Engine!$A:$A,0)),0)} -> 0 | L6: {=IFERROR(INDEX(Signal_Engine!$W:$W,MATCH($B6,Signal_Engine!$A:$A,0)),0)} -> 0 | M6: {=IFERROR(INDEX(Signal_Engine!$X:$X,MATCH($B6,Signal_Engine!$A:$A,0)),0)} -> 4 | N6: {=IFERROR(XLOOKUP($B6,Signal_Engine!$A:$A,Signal_Engine!$AQ:$AQ),0)} -> 0 | O6: {=IFERROR(XLOOKUP($B6,Signal_Engine!$A:$A,Signal_Engine!$AR:$AR),0)} -> 0 | P6: {=IFERROR(XLOOKUP($B6,Signal_Engine!$A:$A,Signal_Engine!$AS:$AS),1)} -> 1 | Q6: {=IFERROR(XLOOKUP($B6,Signal_Engine!$A:$A,Signal_Engine!$AT:$AT),"Neutral / Mixed")} -> Neutral / Mixed | R6: {=IFERROR(XLOOKUP($B6,Signal_Engine!$A:$A,Signal_Engine!$AU:$AU),"")} -> Pts → Bull 0 | Bear 0 | Neutral 155 || Commercial 0 (0) | NonComm 0 (0) | OI 0 (0) | DXY Neutral (0) | RealYield Neutral (0) | S6: {=IF(Q6="Strong Bearish","High-conviction bearish machine pressure.",IF(Q6="Strong Bullish","High-conviction bullish machine pressure.",IF(Q6="Bearish","Bearish machine pressure outweighs bullish evidence.",IF(Q6="Bullish","Bullish machine pressure outweighs bearish evidence.",IF(Q6="Moderate Bearish","Moderate bearish skew; confirm with structure/timing.",IF(Q6="Moderate Bullish","Moderate bullish skew; confirm with structure/timing.","Mixed machine; wait for cleaner alignment."))))))} -> Mixed machine; wait for cleaner alignment. | T6: =IF(Z6="Yes","Live","Manual") -> Live | U6: {=C6} -> Neutral | V6: {=D6} -> Neutral | W6: {=E6} -> Neutral | X6: {=F6} -> Neutral | Y6: =A6 -> 46182.829 | Z6: Yes | AA6: {=IFERROR(INDEX(Signal_Engine!$AF:$AF,MATCH($B6,Signal_Engine!$A:$A,0)),"Auto-connected to Signal_Engine.")} -> RealYield Δ 0.00 | NonComm Δ 0 | Commercial Δ 0 | OI Δ 0
K7: {=IFERROR(INDEX(Signal_Engine!$V:$V,MATCH($B7,Signal_Engine!$A:$A,0)),0)} -> 0 | L7: {=IFERROR(INDEX(Signal_Engine!$W:$W,MATCH($B7,Signal_Engine!$A:$A,0)),0)} -> 0 | M7: {=IFERROR(INDEX(Signal_Engine!$X:$X,MATCH($B7,Signal_Engine!$A:$A,0)),0)} -> 0 | N7: {=IFERROR(INDEX(Signal_Engine!$Y:$Y,MATCH($B7,Signal_Engine!$A:$A,0)),0)} -> 0 | O7: {=IFERROR(INDEX(Signal_Engine!$Z:$Z,MATCH($B7,Signal_Engine!$A:$A,0)),0)} -> 0 | P7: {=IFERROR(INDEX(Signal_Engine!$AA:$AA,MATCH($B7,Signal_Engine!$A:$A,0)),0)} -> 0 | Q7: {=IFERROR(INDEX(Signal_Engine!$AB:$AB,MATCH($B7,Signal_Engine!$A:$A,0)),"Neutral / Mixed")} -> Neutral / Mixed | R7: {=IFERROR(INDEX(Signal_Engine!$AC:$AC,MATCH($B7,Signal_Engine!$A:$A,0)),"0/4 Bullish | 0/4 Bearish | 0/4 Neutral")} -> 0/4 Bullish | 0/4 Bearish | 0/4 Neutral | S7: {=IFERROR(INDEX(Signal_Engine!$AD:$AD,MATCH($B7,Signal_Engine!$A:$A,0)),"Mixed machine; wait for cleaner alignment.")} -> Mixed machine; wait for cleaner alignment.
K8: {=IFERROR(INDEX(Signal_Engine!$V:$V,MATCH($B8,Signal_Engine!$A:$A,0)),0)} -> 0 | L8: {=IFERROR(INDEX(Signal_Engine!$W:$W,MATCH($B8,Signal_Engine!$A:$A,0)),0)} -> 0 | M8: {=IFERROR(INDEX(Signal_Engine!$X:$X,MATCH($B8,Signal_Engine!$A:$A,0)),0)} -> 0 | N8: {=IFERROR(INDEX(Signal_Engine!$Y:$Y,MATCH($B8,Signal_Engine!$A:$A,0)),0)} -> 0 | O8: {=IFERROR(INDEX(Signal_Engine!$Z:$Z,MATCH($B8,Signal_Engine!$A:$A,0)),0)} -> 0 | P8: {=IFERROR(INDEX(Signal_Engine!$AA:$AA,MATCH($B8,Signal_Engine!$A:$A,0)),0)} -> 0 | Q8: {=IFERROR(INDEX(Signal_Engine!$AB:$AB,MATCH($B8,Signal_Engine!$A:$A,0)),"Neutral / Mixed")} -> Neutral / Mixed | R8: {=IFERROR(INDEX(Signal_Engine!$AC:$AC,MATCH($B8,Signal_Engine!$A:$A,0)),"0/4 Bullish | 0/4 Bearish | 0/4 Neutral")} -> 0/4 Bullish | 0/4 Bearish | 0/4 Neutral | S8: {=IFERROR(INDEX(Signal_Engine!$AD:$AD,MATCH($B8,Signal_Engine!$A:$A,0)),"Mixed machine; wait for cleaner alignment.")} -> Mixed machine; wait for cleaner alignment.
K9: {=IFERROR(INDEX(Signal_Engine!$V:$V,MATCH($B9,Signal_Engine!$A:$A,0)),0)} -> 0 | L9: {=IFERROR(INDEX(Signal_Engine!$W:$W,MATCH($B9,Signal_Engine!$A:$A,0)),0)} -> 0 | M9: {=IFERROR(INDEX(Signal_Engine!$X:$X,MATCH($B9,Signal_Engine!$A:$A,0)),0)} -> 0 | N9: {=IFERROR(INDEX(Signal_Engine!$Y:$Y,MATCH($B9,Signal_Engine!$A:$A,0)),0)} -> 0 | O9: {=IFERROR(INDEX(Signal_Engine!$Z:$Z,MATCH($B9,Signal_Engine!$A:$A,0)),0)} -> 0 | P9: {=IFERROR(INDEX(Signal_Engine!$AA:$AA,MATCH($B9,Signal_Engine!$A:$A,0)),0)} -> 0 | Q9: {=IFERROR(INDEX(Signal_Engine!$AB:$AB,MATCH($B9,Signal_Engine!$A:$A,0)),"Neutral / Mixed")} -> Neutral / Mixed | R9: {=IFERROR(INDEX(Signal_Engine!$AC:$AC,MATCH($B9,Signal_Engine!$A:$A,0)),"0/4 Bullish | 0/4 Bearish | 0/4 Neutral")} -> 0/4 Bullish | 0/4 Bearish | 0/4 Neutral | S9: {=IFERROR(INDEX(Signal_Engine!$AD:$AD,MATCH($B9,Signal_Engine!$A:$A,0)),"Mixed machine; wait for cleaner alignment.")} -> Mixed machine; wait for cleaner alignment.
K10: {=IFERROR(INDEX(Signal_Engine!$V:$V,MATCH($B10,Signal_Engine!$A:$A,0)),0)} -> 0 | L10: {=IFERROR(INDEX(Signal_Engine!$W:$W,MATCH($B10,Signal_Engine!$A:$A,0)),0)} -> 0 | M10: {=IFERROR(INDEX(Signal_Engine!$X:$X,MATCH($B10,Signal_Engine!$A:$A,0)),0)} -> 0 | N10: {=IFERROR(INDEX(Signal_Engine!$Y:$Y,MATCH($B10,Signal_Engine!$A:$A,0)),0)} -> 0 | O10: {=IFERROR(INDEX(Signal_Engine!$Z:$Z,MATCH($B10,Signal_Engine!$A:$A,0)),0)} -> 0 | P10: {=IFERROR(INDEX(Signal_Engine!$AA:$AA,MATCH($B10,Signal_Engine!$A:$A,0)),0)} -> 0 | Q10: {=IFERROR(INDEX(Signal_Engine!$AB:$AB,MATCH($B10,Signal_Engine!$A:$A,0)),"Neutral / Mixed")} -> Neutral / Mixed | R10: {=IFERROR(INDEX(Signal_Engine!$AC:$AC,MATCH($B10,Signal_Engine!$A:$A,0)),"0/4 Bullish | 0/4 Bearish | 0/4 Neutral")} -> 0/4 Bullish | 0/4 Bearish | 0/4 Neutral | S10: {=IFERROR(INDEX(Signal_Engine!$AD:$AD,MATCH($B10,Signal_Engine!$A:$A,0)),"Mixed machine; wait for cleaner alignment.")} -> Mixed machine; wait for cleaner alignment.
K11: {=IFERROR(INDEX(Signal_Engine!$V:$V,MATCH($B11,Signal_Engine!$A:$A,0)),0)} -> 0 | L11: {=IFERROR(INDEX(Signal_Engine!$W:$W,MATCH($B11,Signal_Engine!$A:$A,0)),0)} -> 0 | M11: {=IFERROR(INDEX(Signal_Engine!$X:$X,MATCH($B11,Signal_Engine!$A:$A,0)),0)} -> 0 | N11: {=IFERROR(INDEX(Signal_Engine!$Y:$Y,MATCH($B11,Signal_Engine!$A:$A,0)),0)} -> 0 | O11: {=IFERROR(INDEX(Signal_Engine!$Z:$Z,MATCH($B11,Signal_Engine!$A:$A,0)),0)} -> 0 | P11: {=IFERROR(INDEX(Signal_Engine!$AA:$AA,MATCH($B11,Signal_Engine!$A:$A,0)),0)} -> 0 | Q11: {=IFERROR(INDEX(Signal_Engine!$AB:$AB,MATCH($B11,Signal_Engine!$A:$A,0)),"Neutral / Mixed")} -> Neutral / Mixed | R11: {=IFERROR(INDEX(Signal_Engine!$AC:$AC,MATCH($B11,Signal_Engine!$A:$A,0)),"0/4 Bullish | 0/4 Bearish | 0/4 Neutral")} -> 0/4 Bullish | 0/4 Bearish | 0/4 Neutral | S11: {=IFERROR(INDEX(Signal_Engine!$AD:$AD,MATCH($B11,Signal_Engine!$A:$A,0)),"Mixed machine; wait for cleaner alignment.")} -> Mixed machine; wait for cleaner alignment.
K12: {=IFERROR(INDEX(Signal_Engine!$V:$V,MATCH($B12,Signal_Engine!$A:$A,0)),0)} -> 0 | L12: {=IFERROR(INDEX(Signal_Engine!$W:$W,MATCH($B12,Signal_Engine!$A:$A,0)),0)} -> 0 | M12: {=IFERROR(INDEX(Signal_Engine!$X:$X,MATCH($B12,Signal_Engine!$A:$A,0)),0)} -> 0 | N12: {=IFERROR(INDEX(Signal_Engine!$Y:$Y,MATCH($B12,Signal_Engine!$A:$A,0)),0)} -> 0 | O12: {=IFERROR(INDEX(Signal_Engine!$Z:$Z,MATCH($B12,Signal_Engine!$A:$A,0)),0)} -> 0 | P12: {=IFERROR(INDEX(Signal_Engine!$AA:$AA,MATCH($B12,Signal_Engine!$A:$A,0)),0)} -> 0 | Q12: {=IFERROR(INDEX(Signal_Engine!$AB:$AB,MATCH($B12,Signal_Engine!$A:$A,0)),"Neutral / Mixed")} -> Neutral / Mixed | R12: {=IFERROR(INDEX(Signal_Engine!$AC:$AC,MATCH($B12,Signal_Engine!$A:$A,0)),"0/4 Bullish | 0/4 Bearish | 0/4 Neutral")} -> 0/4 Bullish | 0/4 Bearish | 0/4 Neutral | S12: {=IFERROR(INDEX(Signal_Engine!$AD:$AD,MATCH($B12,Signal_Engine!$A:$A,0)),"Mixed machine; wait for cleaner alignment.")} -> Mixed machine; wait for cleaner alignment.
K13: {=IFERROR(INDEX(Signal_Engine!$V:$V,MATCH($B13,Signal_Engine!$A:$A,0)),0)} -> 0 | L13: {=IFERROR(INDEX(Signal_Engine!$W:$W,MATCH($B13,Signal_Engine!$A:$A,0)),0)} -> 0 | M13: {=IFERROR(INDEX(Signal_Engine!$X:$X,MATCH($B13,Signal_Engine!$A:$A,0)),0)} -> 0 | N13: {=IFERROR(INDEX(Signal_Engine!$Y:$Y,MATCH($B13,Signal_Engine!$A:$A,0)),0)} -> 0 | O13: {=IFERROR(INDEX(Signal_Engine!$Z:$Z,MATCH($B13,Signal_Engine!$A:$A,0)),0)} -> 0 | P13: {=IFERROR(INDEX(Signal_Engine!$AA:$AA,MATCH($B13,Signal_Engine!$A:$A,0)),0)} -> 0 | Q13: {=IFERROR(INDEX(Signal_Engine!$AB:$AB,MATCH($B13,Signal_Engine!$A:$A,0)),"Neutral / Mixed")} -> Neutral / Mixed | R13: {=IFERROR(INDEX(Signal_Engine!$AC:$AC,MATCH($B13,Signal_Engine!$A:$A,0)),"0/4 Bullish | 0/4 Bearish | 0/4 Neutral")} -> 0/4 Bullish | 0/4 Bearish | 0/4 Neutral | S13: {=IFERROR(INDEX(Signal_Engine!$AD:$AD,MATCH($B13,Signal_Engine!$A:$A,0)),"Mixed machine; wait for cleaner alignment.")} -> Mixed machine; wait for cleaner alignment.
K14: {=IFERROR(INDEX(Signal_Engine!$V:$V,MATCH($B14,Signal_Engine!$A:$A,0)),0)} -> 0 | L14: {=IFERROR(INDEX(Signal_Engine!$W:$W,MATCH($B14,Signal_Engine!$A:$A,0)),0)} -> 0 | M14: {=IFERROR(INDEX(Signal_Engine!$X:$X,MATCH($B14,Signal_Engine!$A:$A,0)),0)} -> 0 | N14: {=IFERROR(INDEX(Signal_Engine!$Y:$Y,MATCH($B14,Signal_Engine!$A:$A,0)),0)} -> 0 | O14: {=IFERROR(INDEX(Signal_Engine!$Z:$Z,MATCH($B14,Signal_Engine!$A:$A,0)),0)} -> 0 | P14: {=IFERROR(INDEX(Signal_Engine!$AA:$AA,MATCH($B14,Signal_Engine!$A:$A,0)),0)} -> 0 | Q14: {=IFERROR(INDEX(Signal_Engine!$AB:$AB,MATCH($B14,Signal_Engine!$A:$A,0)),"Neutral / Mixed")} -> Neutral / Mixed | R14: {=IFERROR(INDEX(Signal_Engine!$AC:$AC,MATCH($B14,Signal_Engine!$A:$A,0)),"0/4 Bullish | 0/4 Bearish | 0/4 Neutral")} -> 0/4 Bullish | 0/4 Bearish | 0/4 Neutral | S14: {=IFERROR(INDEX(Signal_Engine!$AD:$AD,MATCH($B14,Signal_Engine!$A:$A,0)),"Mixed machine; wait for cleaner alignment.")} -> Mixed machine; wait for cleaner alignment.
K15: {=IFERROR(INDEX(Signal_Engine!$V:$V,MATCH($B15,Signal_Engine!$A:$A,0)),0)} -> 0 | L15: {=IFERROR(INDEX(Signal_Engine!$W:$W,MATCH($B15,Signal_Engine!$A:$A,0)),0)} -> 0 | M15: {=IFERROR(INDEX(Signal_Engine!$X:$X,MATCH($B15,Signal_Engine!$A:$A,0)),0)} -> 0 | N15: {=IFERROR(INDEX(Signal_Engine!$Y:$Y,MATCH($B15,Signal_Engine!$A:$A,0)),0)} -> 0 | O15: {=IFERROR(INDEX(Signal_Engine!$Z:$Z,MATCH($B15,Signal_Engine!$A:$A,0)),0)} -> 0 | P15: {=IFERROR(INDEX(Signal_Engine!$AA:$AA,MATCH($B15,Signal_Engine!$A:$A,0)),0)} -> 0 | Q15: {=IFERROR(INDEX(Signal_Engine!$AB:$AB,MATCH($B15,Signal_Engine!$A:$A,0)),"Neutral / Mixed")} -> Neutral / Mixed | R15: {=IFERROR(INDEX(Signal_Engine!$AC:$AC,MATCH($B15,Signal_Engine!$A:$A,0)),"0/4 Bullish | 0/4 Bearish | 0/4 Neutral")} -> 0/4 Bullish | 0/4 Bearish | 0/4 Neutral | S15: {=IFERROR(INDEX(Signal_Engine!$AD:$AD,MATCH($B15,Signal_Engine!$A:$A,0)),"Mixed machine; wait for cleaner alignment.")} -> Mixed machine; wait for cleaner alignment.
K16: {=IFERROR(INDEX(Signal_Engine!$V:$V,MATCH($B16,Signal_Engine!$A:$A,0)),0)} -> 0 | L16: {=IFERROR(INDEX(Signal_Engine!$W:$W,MATCH($B16,Signal_Engine!$A:$A,0)),0)} -> 0 | M16: {=IFERROR(INDEX(Signal_Engine!$X:$X,MATCH($B16,Signal_Engine!$A:$A,0)),0)} -> 0 | N16: {=IFERROR(INDEX(Signal_Engine!$Y:$Y,MATCH($B16,Signal_Engine!$A:$A,0)),0)} -> 0 | O16: {=IFERROR(INDEX(Signal_Engine!$Z:$Z,MATCH($B16,Signal_Engine!$A:$A,0)),0)} -> 0 | P16: {=IFERROR(INDEX(Signal_Engine!$AA:$AA,MATCH($B16,Signal_Engine!$A:$A,0)),0)} -> 0 | Q16: {=IFERROR(INDEX(Signal_Engine!$AB:$AB,MATCH($B16,Signal_Engine!$A:$A,0)),"Neutral / Mixed")} -> Neutral / Mixed | R16: {=IFERROR(INDEX(Signal_Engine!$AC:$AC,MATCH($B16,Signal_Engine!$A:$A,0)),"0/4 Bullish | 0/4 Bearish | 0/4 Neutral")} -> 0/4 Bullish | 0/4 Bearish | 0/4 Neutral | S16: {=IFERROR(INDEX(Signal_Engine!$AD:$AD,MATCH($B16,Signal_Engine!$A:$A,0)),"Mixed machine; wait for cleaner alignment.")} -> Mixed machine; wait for cleaner alignment.
K17: {=IFERROR(INDEX(Signal_Engine!$V:$V,MATCH($B17,Signal_Engine!$A:$A,0)),0)} -> 0 | L17: {=IFERROR(INDEX(Signal_Engine!$W:$W,MATCH($B17,Signal_Engine!$A:$A,0)),0)} -> 0 | M17: {=IFERROR(INDEX(Signal_Engine!$X:$X,MATCH($B17,Signal_Engine!$A:$A,0)),0)} -> 0 | N17: {=IFERROR(INDEX(Signal_Engine!$Y:$Y,MATCH($B17,Signal_Engine!$A:$A,0)),0)} -> 0 | O17: {=IFERROR(INDEX(Signal_Engine!$Z:$Z,MATCH($B17,Signal_Engine!$A:$A,0)),0)} -> 0 | P17: {=IFERROR(INDEX(Signal_Engine!$AA:$AA,MATCH($B17,Signal_Engine!$A:$A,0)),0)} -> 0 | Q17: {=IFERROR(INDEX(Signal_Engine!$AB:$AB,MATCH($B17,Signal_Engine!$A:$A,0)),"Neutral / Mixed")} -> Neutral / Mixed | R17: {=IFERROR(INDEX(Signal_Engine!$AC:$AC,MATCH($B17,Signal_Engine!$A:$A,0)),"0/4 Bullish | 0/4 Bearish | 0/4 Neutral")} -> 0/4 Bullish | 0/4 Bearish | 0/4 Neutral | S17: {=IFERROR(INDEX(Signal_Engine!$AD:$AD,MATCH($B17,Signal_Engine!$A:$A,0)),"Mixed machine; wait for cleaner alignment.")} -> Mixed machine; wait for cleaner alignment.
K18: {=IFERROR(INDEX(Signal_Engine!$V:$V,MATCH($B18,Signal_Engine!$A:$A,0)),0)} -> 0 | L18: {=IFERROR(INDEX(Signal_Engine!$W:$W,MATCH($B18,Signal_Engine!$A:$A,0)),0)} -> 0 | M18: {=IFERROR(INDEX(Signal_Engine!$X:$X,MATCH($B18,Signal_Engine!$A:$A,0)),0)} -> 0 | N18: {=IFERROR(INDEX(Signal_Engine!$Y:$Y,MATCH($B18,Signal_Engine!$A:$A,0)),0)} -> 0 | O18: {=IFERROR(INDEX(Signal_Engine!$Z:$Z,MATCH($B18,Signal_Engine!$A:$A,0)),0)} -> 0 | P18: {=IFERROR(INDEX(Signal_Engine!$AA:$AA,MATCH($B18,Signal_Engine!$A:$A,0)),0)} -> 0 | Q18: {=IFERROR(INDEX(Signal_Engine!$AB:$AB,MATCH($B18,Signal_Engine!$A:$A,0)),"Neutral / Mixed")} -> Neutral / Mixed | R18: {=IFERROR(INDEX(Signal_Engine!$AC:$AC,MATCH($B18,Signal_Engine!$A:$A,0)),"0/4 Bullish | 0/4 Bearish | 0/4 Neutral")} -> 0/4 Bullish | 0/4 Bearish | 0/4 Neutral | S18: {=IFERROR(INDEX(Signal_Engine!$AD:$AD,MATCH($B18,Signal_Engine!$A:$A,0)),"Mixed machine; wait for cleaner alignment.")} -> Mixed machine; wait for cleaner alignment.
... K51: {=IFERROR(INDEX(Signal_Engine!$V:$V,MATCH($B51,Signal_Engine!$A:$A,0)),0)} -> 0 | L51: {=IFERROR(INDEX(Signal_Engine!$W:$W,MATCH($B51,Signal_Engine!$A:$A,0)),0)} -> 0 | M51: {=IFERROR(INDEX(Signal_Engine!$X:$X,MATCH($B51,Signal_Engine!$A:$A,0)),0)} -> 0 | N51: {=IFERROR(INDEX(Signal_Engine!$Y:$Y,MATCH($B51,Signal_Engine!$A:$A,0)),0)} -> 0 | O51: {=IFERROR(INDEX(Signal_Engine!$Z:$Z,MATCH($B51,Signal_Engine!$A:$A,0)),0)} -> 0 | P51: {=IFERROR(INDEX(Signal_Engine!$AA:$AA,MATCH($B51,Signal_Engine!$A:$A,0)),0)} -> 0 | Q51: {=IFERROR(INDEX(Signal_Engine!$AB:$AB,MATCH($B51,Signal_Engine!$A:$A,0)),"Neutral / Mixed")} -> Neutral / Mixed | R51: {=IFERROR(INDEX(Signal_Engine!$AC:$AC,MATCH($B51,Signal_Engine!$A:$A,0)),"0/4 Bullish | 0/4 Bearish | 0/4 Neutral")} -> 0/4 Bullish | 0/4 Bearish | 0/4 Neutral | S51: {=IFERROR(INDEX(Signal_Engine!$AD:$AD,MATCH($B51,Signal_Engine!$A:$A,0)),"Mixed machine; wait for cleaner alignment.")} -> Mixed machine; wait for cleaner alignment.

Sheet Asset_Config
A1: Asset | B1: Asset Name | C1: Primary Market | D1: Machine Logic | E1: Seasonal Notes | F1: Timing Notes | G1: Default Key Level | H1: Notes | I1: Priority
A2: XAGUSD | B2: Spot Silver | C2: Silver / Precious Metals | D2: DXY + real yields + CFTC silver noncommercial/commercial + OI + calibrated timing. | E2: Seasonality now calibrated from XAGUSD hourly/monthly data; see Seasonality tab. | F2: Bearish: high tends Monday/Sun–Tue; Bullish: low tends Sunday/Sun–Tue; primary decision hour 09:00 ET. | G2: Manual | H2: Uses XAGUSD spot timing + CFTC Silver proxy. SI futures correlation retained in Lead_Lag. | I2: Primary
A3: US30 | B3: Dow Jones / US30 | C3: US equity index | D3: DXY + real yields + TFF/legacy equity positioning proxy + OI + calibrated timing. | E3: Seasonality now calibrated from US30_CFD hourly/monthly data. | F3: Bearish: high tends Monday / low tends Friday; primary hour 09:00 ET. Bullish: low Monday; high Friday. | G3: Manual | H3: Uses US30_CFD timing and TFF/legacy Dow proxy when CFTC pull is available. | I3: Primary
A4: SPX500 | B4: S&P 500 CFD / Index | C4: US equity index | D4: DXY + real yields + TFF S&P proxy + OI + calibrated timing. | E4: Seasonality now calibrated from SPX hourly/monthly data. | F4: Bearish: high Monday / low Friday; bullish: low Monday / high Friday; 09:00 ET dominant. | G4: Manual | H4: Uses SPX timing and CFTC/TFF S&P proxy. Treat as proxy layer for US30 risk. | I4: Optional
A5: NAS100 | B5: Nasdaq / US100 | C5: US growth index | D5: Real yields + DXY + TFF Nasdaq proxy + OI + calibrated timing. | E5: Seasonality now calibrated from NDX hourly/monthly data. | F5: Bearish: high Monday / low Friday; bullish: low Monday / high Friday; 09:00 ET dominant. | G5: Manual | H5: Uses NDX timing and CFTC/TFF Nasdaq proxy; real yields weighted carefully. | I5: Optional
A6: Custom | B6: Custom Instrument | C6: User defined | D6: Define rules manually or import a new asset calibration block. | E6: Define manually | F6: Define manually | G6: Manual | H6: Use dropdowns and manual scoring until calibrated. | I6: Custom

Sheet Seasonality
A1: Asset | B1: Month | C1: Avg Return | D1: Seasonal Bias | E1: Strength | F1: Notes | G1: Rank | H1: Use in Final Read | I1: Source | J1: Last Updated
A2: XAGUSD | B2: January | C2: 0.0548 | D2: Bullish | E2: Strong | F2: Samples 4 | Win 50.0% | Avg range 24.2% | G2: 2 | H2: Yes | I2: Hourly/monthly calibration dataset | J2: 2026-06-09
A3: XAGUSD | B3: February | C3: -0.0045 | D3: Neutral | E3: Weak | F3: Samples 4 | Win 25.0% | Avg range 17.2% | G3: 11 | H3: Optional | I3: Hourly/monthly calibration dataset | J3: 2026-06-09
A4: XAGUSD | B4: March | C4: 0.0352 | D4: Bullish | E4: Strong | F4: Samples 4 | Win 75.0% | Avg range 21.2% | G4: 5 | H4: Yes | I4: Hourly/monthly calibration dataset | J4: 2026-06-09
A5: XAGUSD | B5: April | C5: 0.0065 | D5: Bullish | E5: Moderate | F5: Samples 4 | Win 75.0% | Avg range 16.8% | G5: 10 | H5: Yes | I5: Hourly/monthly calibration dataset | J5: 2026-06-09
A6: XAGUSD | B6: May | C6: 0.0339 | D6: Bullish | E6: Strong | F6: Samples 4 | Win 75.0% | Avg range 17.2% | G6: 6 | H6: Yes | I6: Hourly/monthly calibration dataset | J6: 2026-06-09
A7: XAGUSD | B7: June | C7: -0.0218 | D7: Bearish | E7: Strong | F7: Samples 4 | Win 25.0% | Avg range 11.7% | G7: 12 | H7: Yes | I7: Hourly/monthly calibration dataset | J7: 2026-06-09
A8: XAGUSD | B8: July | C8: 0.0305 | D8: Bullish | E8: Strong | F8: Samples 3 | Win 66.7% | Avg range 12.5% | G8: 9 | H8: Yes | I8: Hourly/monthly calibration dataset | J8: 2026-06-09
A9: XAGUSD | B9: August | C9: 0.0321 | D9: Bullish | E9: Strong | F9: Samples 3 | Win 33.3% | Avg range 12.0% | G9: 8 | H9: Yes | I9: Hourly/monthly calibration dataset | J9: 2026-06-09
A10: XAGUSD | B10: September | C10: 0.0523 | D10: Bullish | E10: Strong | F10: Samples 3 | Win 66.7% | Avg range 15.6% | G10: 3 | H10: Yes | I10: Hourly/monthly calibration dataset | J10: 2026-06-09
A11: XAGUSD | B11: October | C11: 0.0339 | D11: Bullish | E11: Strong | F11: Samples 3 | Win 100.0% | Avg range 15.9% | G11: 7 | H11: Yes | I11: Hourly/monthly calibration dataset | J11: 2026-06-09
A12: XAGUSD | B12: November | C12: 0.075 | D12: Bullish | E12: Strong | F12: Samples 3 | Win 66.7% | Avg range 16.4% | G12: 1 | H12: Yes | I12: Hourly/monthly calibration dataset | J12: 2026-06-09
A13: XAGUSD | B13: December | C13: 0.0468 | D13: Bullish | E13: Strong | F13: Samples 3 | Win 33.3% | Avg range 24.5% | G13: 4 | H13: Yes | I13: Hourly/monthly calibration dataset | J13: 2026-06-09
... A49: NAS100 | B49: December | C49: -0.0053 | D49: Bearish | E49: Moderate | F49: Samples 11 | Win 63.6% | Avg range 7.6% | G49: 11 | H49: Yes | I49: Hourly/monthly calibration dataset | J49: 2026-06-09

Sheet Timing
A1: Asset | B1: Machine State | C1: Weekly High Window | D1: Weekly Low Window | E1: Primary Hour | F1: Secondary Hours | G1: Trap / Continuation Note | H1: Confidence | I1: Sample Size | J1: Source | K1: Last Updated
A2: XAGUSD | B2: Neutral | C2: Friday (35.8%) | Sun–Tue high 35.8% | D2: Sunday (20.7%) | Sun–Tue low 52.5% | E2: High 09:00 ET (15.1%) / Low 18:00 ET (18.4%) | F2: High hrs: 09:00 ET (15.1%), 10:00 ET (8.4%), 13:00 ET (6.7%) | Low hrs: 18:00 ET (18.4%), 09:00 ET (11.2%), 08:00 ET (9.5%) | G2: Baseline mixed-machine timing. Use as reference only; high-before-low 44.7%. | H2: High | I2: 179 weeks | J2: Hourly calibration dataset | K2: 2026-06-09
A3: XAGUSD | B3: Bullish | C3: Friday (62.9%) | Sun–Tue high 10.3% | D3: Sunday (37.1%) | Sun–Tue low 80.4% | E3: High 09:00 ET (15.5%) / Low 18:00 ET (26.8%) | F3: High hrs: 09:00 ET (15.1%), 10:00 ET (8.4%), 13:00 ET (6.7%) | Low hrs: 18:00 ET (18.4%), 09:00 ET (11.2%), 08:00 ET (9.5%) | G3: Bullish template: weekly low tends early; high-before-low only 7.2%. Watch early dip into support then late-week expansion. | H3: Moderate-High | I3: 97 weeks | J3: Hourly calibration dataset | K3: 2026-06-09
A4: XAGUSD | B4: Bearish | C4: Monday (29.3%) | Sun–Tue high 65.9% | D4: Friday (39.0%) | Sun–Tue low 19.5% | E4: High 09:00 ET (14.6%) / Low 09:00 ET (14.6%) | F4: High hrs: 09:00 ET (15.1%), 10:00 ET (8.4%), 13:00 ET (6.7%) | Low hrs: 18:00 ET (18.4%), 09:00 ET (11.2%), 08:00 ET (9.5%) | G4: Bearish template: weekly high tends early; high-before-low 89.0%. Watch early-week rally/fake reclaim into rejection. | H4: Moderate-High | I4: 82 weeks | J4: Hourly calibration dataset | K4: 2026-06-09
A5: XAGUSD | B5: Expansion | C5: Friday (47.1%) | Sun–Tue high 31.8% | D5: Sunday (29.4%) | Sun–Tue low 62.4% | E5: High 09:00 ET (10.6%) / Low 18:00 ET (24.7%) | F5: High hrs: 09:00 ET (15.1%), 10:00 ET (8.4%), 13:00 ET (6.7%) | Low hrs: 18:00 ET (18.4%), 09:00 ET (11.2%), 08:00 ET (9.5%) | G5: Expansion profile: use only after machine aligns and range expands; high-before-low 40.0%. | H5: Moderate-High | I5: 85 weeks | J5: Hourly calibration dataset | K5: 2026-06-09
A6: US30 | B6: Neutral | C6: Friday (35.8%) | Sun–Tue high 34.1% | D6: Friday (26.3%) | Sun–Tue low 44.1% | E6: High 09:00 ET (15.6%) / Low 09:00 ET (14.5%) | F6: High hrs: 09:00 ET (15.6%), 10:00 ET (13.4%), 12:00 ET (11.7%) | Low hrs: 09:00 ET (14.5%), 10:00 ET (11.2%), 15:00 ET (7.8%) | G6: Baseline mixed-machine timing. Use as reference only; high-before-low 43.0%. | H6: High | I6: 179 weeks | J6: Hourly calibration dataset | K6: 2026-06-09
A7: US30 | B7: Bullish | C7: Friday (58.7%) | Sun–Tue high 7.7% | D7: Monday (33.7%) | Sun–Tue low 64.4% | E7: High 10:00 ET (16.3%) / Low 09:00 ET (15.4%) | F7: High hrs: 09:00 ET (15.6%), 10:00 ET (13.4%), 12:00 ET (11.7%) | Low hrs: 09:00 ET (14.5%), 10:00 ET (11.2%), 15:00 ET (7.8%) | G7: Bullish template: weekly low tends early; high-before-low only 12.5%. Watch early dip into support then late-week expansion. | H7: Moderate-High | I7: 104 weeks | J7: Hourly calibration dataset | K7: 2026-06-09
A8: US30 | B8: Bearish | C8: Monday (40.0%) | Sun–Tue high 70.7% | D8: Friday (54.7%) | Sun–Tue low 16.0% | E8: High 09:00 ET (22.7%) / Low 09:00 ET (13.3%) | F8: High hrs: 09:00 ET (15.6%), 10:00 ET (13.4%), 12:00 ET (11.7%) | Low hrs: 09:00 ET (14.5%), 10:00 ET (11.2%), 15:00 ET (7.8%) | G8: Bearish template: weekly high tends early; high-before-low 85.3%. Watch early-week rally/fake reclaim into rejection. | H8: Moderate-High | I8: 75 weeks | J8: Hourly calibration dataset | K8: 2026-06-09
A9: US30 | B9: Expansion | C9: Friday (36.1%) | Sun–Tue high 37.3% | D9: Friday (31.3%) | Sun–Tue low 44.6% | E9: High 12:00 ET (12.0%) / Low 09:00 ET (9.6%) | F9: High hrs: 09:00 ET (15.6%), 10:00 ET (13.4%), 12:00 ET (11.7%) | Low hrs: 09:00 ET (14.5%), 10:00 ET (11.2%), 15:00 ET (7.8%) | G9: Expansion profile: use only after machine aligns and range expands; high-before-low 45.8%. | H9: Moderate-High | I9: 83 weeks | J9: Hourly calibration dataset | K9: 2026-06-09
A10: SPX500 | B10: Neutral | C10: Friday (38.1%) | Sun–Tue high 30.7% | D10: Monday (30.4%) | Sun–Tue low 47.1% | E10: High 09:00 ET (35.6%) / Low 09:00 ET (34.4%) | F10: High hrs: 09:00 ET (35.6%), 15:00 ET (21.6%), 14:00 ET (10.9%) | Low hrs: 09:00 ET (34.4%), 10:00 ET (15.3%), 15:00 ET (14.4%) | G10: Baseline mixed-machine timing. Use as reference only; high-before-low 42.6%. | H10: High | I10: 596 weeks | J10: Hourly calibration dataset | K10: 2026-06-09
A11: SPX500 | B11: Bullish | C11: Friday (61.6%) | Sun–Tue high 6.8% | D11: Monday (49.4%) | Sun–Tue low 71.9% | E11: High 15:00 ET (27.3%) / Low 09:00 ET (44.9%) | F11: High hrs: 09:00 ET (35.6%), 15:00 ET (21.6%), 14:00 ET (10.9%) | Low hrs: 09:00 ET (34.4%), 10:00 ET (15.3%), 15:00 ET (14.4%) | G11: Bullish template: weekly low tends early; high-before-low only 9.7%. Watch early dip into support then late-week expansion. | H11: High | I11: 352 weeks | J11: Hourly calibration dataset | K11: 2026-06-09
A12: SPX500 | B12: Bearish | C12: Monday (38.1%) | Sun–Tue high 65.2% | D12: Friday (53.7%) | Sun–Tue low 11.5% | E12: High 09:00 ET (49.6%) / Low 15:00 ET (22.1%) | F12: High hrs: 09:00 ET (35.6%), 15:00 ET (21.6%), 14:00 ET (10.9%) | Low hrs: 09:00 ET (34.4%), 10:00 ET (15.3%), 15:00 ET (14.4%) | G12: Bearish template: weekly high tends early; high-before-low 90.2%. Watch early-week rally/fake reclaim into rejection. | H12: High | I12: 244 weeks | J12: Hourly calibration dataset | K12: 2026-06-09
... A17: NAS100 | B17: Expansion | C17: Friday (36.8%) | Sun–Tue high 36.4% | D17: Monday (35.4%) | Sun–Tue low 47.8% | E17: High 09:00 ET (40.2%) / Low 09:00 ET (38.8%) | F17: High hrs: 09:00 ET (39.3%), 15:00 ET (20.1%), 10:00 ET (9.9%) | Low hrs: 09:00 ET (39.9%), 10:00 ET (15.1%), 15:00 ET (14.1%) | G17: Expansion profile: use only after machine aligns and range expands; high-before-low 46.4%. | H17: High | I17: 291 weeks | J17: Hourly calibration dataset | K17: 2026-06-09

Sheet Structure
A1: Asset | B1: Current Price | C1: Key Level | D1: Structure Status | E1: Acceptance | F1: Structure Score | G1: Note | H1: Last Updated | I1: Manual Update Sheet
A2: XAGUSD | B2: Manual | C2: 68 / manual | D2: Below key level | E2: Pending confirmation | F2: -1 | G2: Update manually based on weekly close / acceptance | H2: Manual | I2: Structure
A3: US30 | B3: Manual | C3: Manual | D3: At decision zone | E3: Pending confirmation | F3: 0 | G3: Update manually from higher-timeframe structure | H3: Manual | I3: Structure
A4: SPX500 | B4: Manual | C4: Manual | D4: At decision zone | E4: Pending confirmation | F4: 0 | G4: Optional future asset | H4: Manual | I4: Structure
A5: NAS100 | B5: Manual | C5: Manual | D5: At decision zone | E5: Pending confirmation | F5: 0 | G5: Optional future asset | H5: Manual | I5: Structure
A6: Custom | B6: Manual | C6: Manual | D6: At decision zone | E6: Pending confirmation | F6: 0 | G6: User-defined | H6: Manual | I6: Structure

Sheet Data_Log
A1: Date | B1: Asset | C1: Source | D1: Metric | E1: Previous | F1: Current | G1: Change | H1: Direction | I1: Machine Impact | J1: Notes
A2: 46180.22 | B2: XAGUSD | C2: Manual / COT | D2: Managed Money | H2: Bearish | I2: Bearish | J2: Log weekly COT changes here
A3: 46180.22 | B3: XAGUSD | C3: Manual / COT | D3: Open Interest | H3: Bearish | I3: Bearish | J3: Log OI changes here
A4: 46180.22 | B4: XAGUSD | C4: FRED / chart | D4: Real Yields | H4: Bearish | I4: Bearish | J4: Daily or weekly update
A5: 46180.22 | B5: XAGUSD | C5: DXY chart | D5: Dollar Index | H5: Bearish | I5: Bearish | J5: Daily or weekly update

Sheet Lists
A1: Directional Status | B1: Machine Bias | C1: Structure Status | D1: Signal Strength | E1: Assets
A2: Bullish | B2: Strong Bullish | C2: Above key level | D2: Strong | E2: XAGUSD
A3: Neutral | B3: Bullish Bias | C3: Below key level | D3: Moderate | E3: US30
A4: Bearish | B4: Neutral / Mixed | C4: At decision zone | D4: Weak | E4: SPX500
B5: Bearish Bias | C5: Rejecting resistance | D5: Conflict | E5: NAS100
B6: Strong Bearish | C6: Holding support | E6: Custom
C7: Acceptance lower
C8: Acceptance higher

Sheet Instructions
A1: Market Machine v4.6 — Final Calibrated Living Engine
A3: What changed in this version: | D3: Notes | E3: Frequency
A4: 1. Timing layer is populated from uploaded hourly datasets for XAGUSD, US30, SPX500, and NAS100. | D4: XAGUSD, US30, SPX500, NAS100, or Custom | E4: Anytime
A5: 2. Seasonality layer is populated from uploaded monthly/hourly-calibrated data for the same core assets. | D5: Use Bullish / Neutral / Bearish. The dashboard calculates bullish, bearish, and neutral scores automatically. | E5: Daily / Weekly
A6: 3. Calibration support sheets were added: Timing_Calibration, Calendar_Alerts, Lead_Lag, Gap_Behavior, Expansion_Profile, Sequence_Stats, and Calibration_Data_Coverage. | D6: Default: DXY 30%, Real Yields 30%, Managed Money 25%, OI 15%. | E6: As refined
A7: 4. Signal_Engine now uses asset-coded CFTC proxy keys so CFTC_Raw can support XAGUSD, US30, SPX500, and NAS100 after the updated refreshCFTC() script runs. | D7: Current price, key level, acceptance/rejection, decision zone. | E7: Before trading window
A8: 5. AppsScript_Code was upgraded with a dual CFTC pull: Legacy for commodities/legacy series and TFF for financial futures proxies. | D8: Current month flows into Dashboard automatically for selected asset. | E8: Monthly
D9: Bearish and bullish timing profiles can be different. | E9: After data studies
A10: Activation steps: | D10: The machine summarizes evidence; it does not replace discipline. | E10: Every review
A11: A. Upload this workbook to Google Sheets and convert/save as Google Sheets.
A12: B. Extensions → Apps Script → paste AppsScript_Code contents. | D12: No single variable should dominate without context. | E12: Always
A13: C. Run refreshFRED().
A14: D. Run refreshCFTC(). | D14: The sheet is the brain; the app is the face. | E14: Later
A15: E. Return to Dashboard and choose asset from the dropdown.
A17: Interpretation rules:
A18: Machine score is live/weekly and should be read with the Timing layer, not in isolation.
A19: Timing layer is calibrated historical context; it is not a command to enter a trade.
A20: For bearish machine states, early-week high window and Friday low tendencies are prioritized.
A21: For bullish machine states, early-week low window and Friday high tendencies are prioritized.
A23: V4.7 BRIEFING / HEALTH / AI SCAFFOLD
A24: 1 | B24: Use Briefing tab first. It is the front-page market-weather read.
A25: 2 | B25: Use Dashboard for the detailed machine score and drill-down.
A26: 3 | B26: Use Health_Check after refreshAll() to verify feeds are alive.
A27: 4 | B27: Use Alert_Rules as the calendar/notification logic map.
A28: 5 | B28: Use AI_Prompt_Builder for manual AI briefing until API integration is desired.
A29: 6 | B29: AI is optional. The deterministic machine remains the primary source of truth.
A30: 7 | B30: Future app: Streamlit or web app should read Briefing + Dashboard + Signal_Engine.
A31: 8 | B31: Do not store API keys directly in a shared spreadsheet.
A32: 9 | B32: Run refreshFRED daily and refreshCFTC weekly; refreshAll can run both.
A33: 10 | B33: Use Notification_Log as a future output sink for automated email/app/calendar briefings.
A34: 11 | B34: Keep v4.6/v4.7 master archived before making major changes.

Sheet Live_Inputs
A1: Asset | B1: Variable | C1: Source | D1: Status | E1: Latest Value | F1: Last Update | G1: Auto/Manual | H1: Threshold / Rule | I1: Raw Sheet | J1: Notes
A2: XAGUSD | B2: DXY | C2: TradingView webhook / manual | D2: Bearish | E2: Manual | F2: Manual | G2: Manual | H2: DXY rising = Bearish Silver | I2: Webhook_Log | J2: Replace via webhook or manual update.
A3: XAGUSD | B3: Real Yields | C3: FRED DFII10 | D3: Bearish | E3: 2.11 | F3: 46180.553 | G3: Auto | H3: Real yields rising = Bearish Silver | I3: FRED_Raw | J3: refreshFRED() fills FRED_Raw.
A4: XAGUSD | B4: Managed Money | C4: CFTC COT | D4: Bullish | E4: 23926 | F4: 46175 | G4: Weekly Auto / Manual | H4: Managed money liquidating = Bearish Silver | I4: CFTC_Raw | J4: refreshCFTC() fills CFTC_Raw; status can be formula-refined.
A5: XAGUSD | B5: Open Interest | C5: CFTC / exchange | D5: Bullish | E5: 102809 | F5: 46175 | G5: Weekly Auto / Manual | H5: OI contracting with liquidation = Bearish Silver | I5: CFTC_Raw | J5: Use CFTC or exchange OI.
A6: US30 | B6: DXY | C6: TradingView webhook / manual | D6: Neutral | E6: Manual | F6: Manual | G6: Manual | H6: DXY rising often risk-off / Bearish risk assets | I6: Webhook_Log | J6: Replace via webhook or manual update.
A7: US30 | B7: Real Yields | C7: FRED DFII10 | D7: Bearish | E7: 2.11 | F7: 46180.553 | G7: Auto | H7: Real yields rising = pressure on risk assets | I7: FRED_Raw | J7: refreshFRED() fills FRED_Raw.
A8: US30 | B8: Managed Money | C8: CFTC / futures proxy | D8: Neutral | E8: Manual | F8: Manual | G8: Weekly Auto / Manual | H8: Risk positioning deteriorating = Bearish risk assets | I8: CFTC_Raw | J8: Use Dow/YM/TFF when mapped.
A9: US30 | B9: Open Interest | C9: CFTC / exchange | D9: Neutral | E9: Manual | F9: Manual | G9: Weekly Auto / Manual | H9: OI contraction can signal participation loss | I9: CFTC_Raw | J9: Use futures OI if available.
A10: SPX500 | B10: DXY | C10: TradingView webhook / manual | D10: Neutral | E10: Manual | F10: Manual | G10: Manual | H10: DXY rising can pressure risk assets | I10: Webhook_Log | J10: Optional future asset.
A11: NAS100 | B11: Real Yields | C11: FRED DFII10 | D11: Bearish | E11: 2.11 | F11: 46180.553 | G11: Auto | H11: Real yields important for growth assets | I11: FRED_Raw | J11: Optional future asset.

Sheet Source_Map
A1: Data Pipe | B1: Primary Source | C1: URL / Endpoint | D1: Update Frequency | E1: Method | F1: Requires Keys | G1: Feeds Sheet | H1: Notes
A2: Real Yields | B2: FRED DFII10 / DGS10 | C2: https://fred.stlouisfed.org/graph/fredgraph.csv | D2: Daily / on demand | E2: Apps Script refreshFRED() | F2: No | G2: FRED_Raw | H2: Pulls recent real and nominal 10Y yields.
A3: CFTC Legacy | B3: CFTC Legacy Futures Only | C3: https://publicreporting.cftc.gov/resource/6dca-aqww.json | D3: Weekly / after Friday release | E3: Apps Script refreshCFTC() | F3: No | G3: CFTC_Raw | H3: Used for metals and USD Index where commercial/noncommercial reporting is direct.
A4: CFTC TFF | B4: CFTC Traders in Financial Futures | C4: https://publicreporting.cftc.gov/resource/gpe5-46if.json | D4: Weekly / after Friday release | E4: Apps Script refreshCFTC() | F4: No | G4: CFTC_Raw | H4: Used as cleaner financial futures proxy for US30/SPX500/NAS100 where available.
A5: DXY / Structure | B5: TradingView webhook | C5: User-deployed Apps Script Web App URL | D5: Event based | E5: TradingView alert → doPost(e) | F5: TradingView alert access | G5: Webhook_Log / Live_Inputs | H5: Manual fallback remains available.
A6: Timing / Seasonality | B6: Uploaded hourly datasets | C6: Internal calibration sheets | D6: Static until next import | E6: Manual update from data study | F6: No | G6: Timing / Seasonality | H6: This version includes calibration data already.
A8: Briefing Front Page | B8: Internal formulas | C8: Briefing | D8: Every recalculation | E8: Formula | F8: No | G8: Briefing | H8: Compact market-weather output.
A9: Health Check | B9: Internal formulas | C9: Health_Check | D9: Every recalculation | E9: Formula | F9: No | G9: Health_Check | H9: PASS/REVIEW diagnostics.
A10: AI Prompt Builder | B10: Internal formulas | C10: AI_Prompt_Builder | D10: On demand | E10: Formula | F10: No | G10: AI_Prompt_Builder | H10: Copy-paste AI briefing scaffold.
A11: Economic Calendar | B11: Manual / future feed | C11: Economic_Calendar | D11: Manual | E11: Manual/API future | F11: Optional | G11: Economic_Calendar | H11: Event risk/context layer.
A12: Notification Log | B12: Apps Script future | C12: Notification_Log | D12: On trigger | E12: Script | F12: No | G12: Notification_Log | H12: Records sent briefings.
A13: App Roadmap | B13: Internal docs | C13: App_Roadmap | D13: Static | E13: Manual | F13: No | G13: App_Roadmap | H13: Development pathway.
A14: Alert Rules | B14: Internal rules | C14: Alert_Rules | D14: Static | E14: Manual | F14: No | G14: Alert_Rules | H14: Calendar-style alert logic.

Sheet FRED_Raw
A1: Date | B1: DFII10 | C1: DGS10 | D1: Source | E1: Pulled At | F1: Notes

Sheet CFTC_Raw
A1: Report Date | B1: Market | C1: Open Interest | D1: Commercial Long | E1: Commercial Short | F1: Noncommercial Long | G1: Noncommercial Short | H1: Nonreportable Long | I1: Nonreportable Short | J1: Pulled At | K1: Source
A2: 46175 | B2: XAGUSD | C2: 102809 | D2: 25782 | E2: 68443 | F2: 33933 | G2: 10007 | H2: 28097 | I2: 9362 | J2: 46182.829 | K2: legacy | SILVER - COMMODITY EXCHANGE INC.
A3: 46168 | B3: XAGUSD | C3: 18145 | D3: 0 | E3: 0 | F3: 6478 | G3: 7181 | H3: 10231 | I3: 9528 | J3: 46182.829 | K3: legacy | MICRO SILVER - COMMODITY EXCHANGE INC.
A4: 46168 | B4: XAGUSD | C4: 101744 | D4: 27605 | E4: 68498 | F4: 32758 | G4: 10535 | H4: 27301 | I4: 8631 | J4: 46182.829 | K4: legacy | SILVER - COMMODITY EXCHANGE INC.
A5: 46161 | B5: XAGUSD | C5: 100751 | D5: 27108 | E5: 69776 | F5: 34591 | G5: 9920 | H5: 26423 | I5: 8426 | J5: 46182.829 | K5: legacy | SILVER - COMMODITY EXCHANGE INC.
A6: 46154 | B6: XAGUSD | C6: 103800 | D6: 27341 | E6: 70987 | F6: 36569 | G6: 10458 | H6: 27802 | I6: 10267 | J6: 46182.829 | K6: legacy | SILVER - COMMODITY EXCHANGE INC.
A7: 46147 | B7: XAGUSD | C7: 96932 | D7: 26094 | E7: 66629 | F7: 32965 | G7: 9073 | H7: 25811 | I7: 9168 | J7: 46182.829 | K7: legacy | SILVER - COMMODITY EXCHANGE INC.
A8: 46140 | B8: XAGUSD | C8: 101275 | D8: 29676 | E8: 70128 | F8: 31314 | G8: 7154 | H8: 25462 | I8: 9170 | J8: 46182.829 | K8: legacy | SILVER - COMMODITY EXCHANGE INC.
A9: 46133 | B9: XAGUSD | C9: 115462 | D9: 32357 | E9: 73342 | F9: 33233 | G9: 9513 | H9: 26253 | I9: 8988 | J9: 46182.829 | K9: legacy | SILVER - COMMODITY EXCHANGE INC.
A10: 46126 | B10: XAGUSD | C10: 116983 | D10: 32338 | E10: 72471 | F10: 32391 | G10: 8829 | H10: 25765 | I10: 9194 | J10: 46182.829 | K10: legacy | SILVER - COMMODITY EXCHANGE INC.
A11: 46119 | B11: XAGUSD | C11: 115138 | D11: 28211 | E11: 67126 | F11: 32810 | G11: 9393 | H11: 24908 | I11: 9410 | J11: 46182.829 | K11: legacy | SILVER - COMMODITY EXCHANGE INC.
A12: 46112 | B12: XAGUSD | C12: 115169 | D12: 29892 | E12: 68749 | F12: 33463 | G12: 9559 | H12: 24465 | I12: 9512 | J12: 46182.829 | K12: legacy | SILVER - COMMODITY EXCHANGE INC.
A13: 46105 | B13: XAGUSD | C13: 113164 | D13: 29511 | E13: 69799 | F13: 33938 | G13: 9265 | H13: 24555 | I13: 8940 | J13: 46182.829 | K13: legacy | SILVER - COMMODITY EXCHANGE INC.
... A121: 45971 | B121: NAS100 | C121: 309882 | D121: 148918 | E121: 210654 | F121: 95865 | G121: 46909 | H121: 45831 | I121: 33051 | J121: 46182.829 | K121: legacy | NASDAQ-100 Consolidated - CHICAGO MERCANTILE EXCHANGE

Sheet Webhook_Log
A1: Received At | B1: Asset | C1: Variable | D1: Status | E1: Price | F1: Time | G1: Ticker | H1: Raw JSON | I1: Notes

Sheet AppsScript_Code
A1: // GOOGLE APPS SCRIPT — MARKET MACHINE v4.7 BRIEFING ENGINE
A2: // Copy everything below into Extensions → Apps Script.
A3: // Run refreshAll() first, then run generateBriefingLog() to test briefing logging.
A4: // Optional: run installTriggers() to schedule daily FRED and weekly CFTC refreshes.
A6: const CONFIG = {
A7: fredSeries: {
A8: realYield10Y: 'DFII10',
A9: nominal10Y: 'DGS10'
A10: },
A11: fredCsvBase: 'https://fred.stlouisfed.org/graph/fredgraph.csv?id=',
A12: cftcEndpoints: {
A13: legacy: 'https://publicreporting.cftc.gov/resource/6dca-aqww.json',
... A281: }

Sheet Script_Setup
A1: Market Machine Live Activation — v4.4 Signal Engine
A2: Step | B2: Action | C2: Where | D2: Expected Result | E2: Status | F2: Notes
A3: 1 | B3: Upload this workbook to Google Sheets and save as native Google Sheets. | C3: Google Drive / Sheets | D3: Extensions menu appears. | E3: Required | F3: Excel cannot run Apps Script.
A4: 2 | B4: Open AppsScript_Code tab, copy all lines, paste into Extensions → Apps Script, save. | C4: Google Sheets | D4: Functions appear: refreshFRED, refreshCFTC, refreshAll, installTriggers. | E4: Required | F4: Line 1 is commented and safe to paste.
A5: 3 | B5: Run refreshFRED. | C5: Apps Script | D5: FRED_Raw populates; Live_Inputs real yields update. | E5: Required | F5: If FRED times out, rerun. Script has retry logic.
A6: 4 | B6: Run refreshCFTC. | C6: Apps Script | D6: CFTC_Raw populates; Live_Inputs managed money/open interest update. | E6: Required | F6: CFTC endpoint is 6dca-aqww.
A7: 5 | B7: Return to Signal_Engine tab. | C7: Google Sheets | D7: Commercial Net, Noncommercial Net, OI Change, signals, weighted scores calculate. | E7: Required | F7: This is the brain between raw data and dashboard.
A8: 6 | B8: Open Dashboard and select asset. | C8: Dashboard | D8: Machine score, seasonality, timing, structure, final read update. | E8: Required | F8: XAGUSD is most complete right now.
A9: 7 | B9: Optional: deploy doPost as Web App and connect TradingView alerts. | C9: Apps Script / TradingView | D9: DXY or structure webhooks update Live_Inputs. | E9: Optional | F9: Webhook is the next pipe after FRED/CFTC.
A10: 8 | B10: Optional: installTriggers(). | C10: Apps Script | D10: FRED refreshes daily; CFTC refreshes Friday afternoon. | E10: Optional | F10: Only run after manual tests work.

Sheet TradingView_Webhooks
A1: TRADINGVIEW WEBHOOK PAYLOADS
A2: Use Case | B2: Asset | C2: Variable | D2: Status | E2: JSON Message | F2: Notes
A3: DXY bullish dollar pressure | B3: XAGUSD | C3: DXY | D3: Bearish | E3: {"asset":"XAGUSD","variable":"DXY","status":"Bearish","price":"{{close}}","time":"{{time}}","ticker":"{{ticker}}"} | F3: Use when DXY condition implies bearish silver.
A4: DXY weakness | B4: XAGUSD | C4: DXY | D4: Bullish | E4: {"asset":"XAGUSD","variable":"DXY","status":"Bullish","price":"{{close}}","time":"{{time}}","ticker":"{{ticker}}"} | F4: Use when DXY weakness supports silver.
A5: Structure break | B5: XAGUSD | C5: Structure | D5: Bearish | E5: {"asset":"XAGUSD","variable":"Structure","status":"Bearish","price":"{{close}}","time":"{{time}}","ticker":"{{ticker}}"} | F5: Use for structure/acceptance events.
A6: US30 risk pressure | B6: US30 | C6: DXY | D6: Bearish | E6: {"asset":"US30","variable":"DXY","status":"Bearish","price":"{{close}}","time":"{{time}}","ticker":"{{ticker}}"} | F6: Use when dollar/yield/risk conditions pressure US30.

Sheet Signal_Engine
A1: Asset | B1: CFTC Proxy Key | C1: Latest Report Date | D1: Previous Report Date | E1: Open Interest | F1: Prev OI | G1: OI Change | H1: Commercial Net | I1: Prev Commercial Net | J1: Commercial Change | K1: Noncommercial Net | L1: Prev Noncommercial Net | M1: Noncommercial Change | N1: Latest Real Yield | O1: Prior Real Yield | P1: Real Yield Change | Q1: Real Yield Signal | R1: Positioning Signal | S1: Commercial Context | T1: Open Interest Signal | U1: DXY Signal | V1: Bullish Count | W1: Bearish Count | X1: Neutral Count | Y1: Weighted Bullish % | Z1: Weighted Bearish % | AA1: Weighted Neutral % | AB1: Machine Bias | AC1: Evidence Text | AD1: Interpretation | AE1: Last Updated | AF1: Signal Notes | AG1: Commercial Alert | AH1: Positioning Alert | AI1: Commercial Score | AJ1: Positioning Score | AK1: OI Score | AL1: DXY Score | AM1: Real Yield Score | AN1: Bullish Points | AO1: Bearish Points | AP1: Neutral Points | AQ1: Final Bullish % | AR1: Final Bearish % | AS1: Final Neutral % | AT1: Final Machine Reading | AU1: Final Score Notes
A2: XAGUSD | B2: XAGUSD | C2: =IF(COUNTIFS(CFTC_Raw!$B:$B,$B2)=0,"",MAXIFS(CFTC_Raw!$A:$A,CFTC_Raw!$B:$B,$B2)) -> 46175 | D2: =IF($C2="","",IF(COUNTIFS(CFTC_Raw!$B:$B,$B2,CFTC_Raw!$A:$A,"<"&$C2)=0,"",MAXIFS(CFTC_Raw!$A:$A,CFTC_Raw!$B:$B,$B2,CFTC_Raw!$A:$A,"<"&$C2))) -> 46168 | E2: =IF($C2="",0,SUMIFS(CFTC_Raw!$C:$C,CFTC_Raw!$B:$B,$B2,CFTC_Raw!$A:$A,$C2)) -> 102809 | F2: =IF($D2="",0,SUMIFS(CFTC_Raw!$C:$C,CFTC_Raw!$B:$B,$B2,CFTC_Raw!$A:$A,$D2)) -> 119889 | G2: =IFERROR(E2-F2,0) -> -17080 | H2: =IF($C2="",0,SUMIFS(CFTC_Raw!$D:$D,CFTC_Raw!$B:$B,$B2,CFTC_Raw!$A:$A,$C2)-SUMIFS(CFTC_Raw!$E:$E,CFTC_Raw!$B:$B,$B2,CFTC_Raw!$A:$A,$C2)) -> -42661 | I2: =IF($D2="",0,SUMIFS(CFTC_Raw!$D:$D,CFTC_Raw!$B:$B,$B2,CFTC_Raw!$A:$A,$D2)-SUMIFS(CFTC_Raw!$E:$E,CFTC_Raw!$B:$B,$B2,CFTC_Raw!$A:$A,$D2)) -> -40893 | J2: =IFERROR(H2-I2,0) -> -1768 | K2: =IF($C2="",0,SUMIFS(CFTC_Raw!$F:$F,CFTC_Raw!$B:$B,$B2,CFTC_Raw!$A:$A,$C2)-SUMIFS(CFTC_Raw!$G:$G,CFTC_Raw!$B:$B,$B2,CFTC_Raw!$A:$A,$C2)) -> 23926 | L2: =IF($D2="",0,SUMIFS(CFTC_Raw!$F:$F,CFTC_Raw!$B:$B,$B2,CFTC_Raw!$A:$A,$D2)-SUMIFS(CFTC_Raw!$G:$G,CFTC_Raw!$B:$B,$B2,CFTC_Raw!$A:$A,$D2)) -> 21520 | M2: =IFERROR(K2-L2,0) -> 2406 | N2: =IFERROR(VALUE(LOOKUP(2,1/(FRED_Raw!$B$2:$B$10000<>""),FRED_Raw!$B$2:$B$10000)),0) -> 0 | O2: {=IFERROR(VALUE(INDEX(FRED_Raw!$B$2:$B$10000,MAX(1,MATCH(2,1/(FRED_Raw!$B$2:$B$10000<>""),1)-5))),0)} -> 0 | P2: =IFERROR(VALUE(N2)-VALUE(O2),0) -> 0 | Q2: =IF(P2>0.05,"Bearish",IF(P2<-0.05,"Bullish","Neutral")) -> Neutral | R2: =IF($M2="","Neutral",IF($M2<0,"Bearish",IF($M2>0,"Bullish","Neutral"))) -> Bullish | S2: =IF($J2="","Neutral",IF($J2>10000,"Bullish",IF($J2<-10000,"Bearish","Neutral"))) -> Neutral | T2: =IF(OR($G2="",$M2=""),"Neutral",IF(AND($G2<0,$M2<0),"Bearish",IF(AND($G2>0,$M2>0),"Bullish","Neutral"))) -> Neutral | U2: {=IFERROR(XLOOKUP($A2&"|DXY",Live_Inputs!$A$2:$A$200&"|"&Live_Inputs!$B$2:$B$200,Live_Inputs!$D$2:$D$200),"Neutral")} -> Neutral | V2: =IF($U2="Bullish",1,0)+IF($Q2="Bullish",1,0)+IF($R2="Bullish",1,0)+IF($T2="Bullish",1,0) -> 1 | W2: =IF($U2="Bearish",1,0)+IF($Q2="Bearish",1,0)+IF($R2="Bearish",1,0)+IF($T2="Bearish",1,0) -> 0 | X2: =IF($U2="Neutral",1,0)+IF($Q2="Neutral",1,0)+IF($R2="Neutral",1,0)+IF($T2="Neutral",1,0) -> 3 | Y2: =IF($U2="Bullish",0.3,0)+IF($Q2="Bullish",0.3,0)+IF($R2="Bullish",0.25,0)+IF($T2="Bullish",0.15,0) -> 0.25 | Z2: =IF($U2="Bearish",0.3,0)+IF($Q2="Bearish",0.3,0)+IF($R2="Bearish",0.25,0)+IF($T2="Bearish",0.15,0) -> 0 | AA2: =IF($U2="Neutral",0.3,0)+IF($Q2="Neutral",0.3,0)+IF($R2="Neutral",0.25,0)+IF($T2="Neutral",0.15,0) -> 0.75 | AB2: =IF($Z2>=0.75,"Strong Bearish",IF($Z2>=0.55,"Bearish Bias",IF($Y2>=0.75,"Strong Bullish",IF($Y2>=0.55,"Bullish Bias","Neutral / Mixed")))) -> Neutral / Mixed | AC2: =$V2&"/4 Bullish | "&$W2&"/4 Bearish | "&$X2&"/4 Neutral" -> 1/4 Bullish | 0/4 Bearish | 3/4 Neutral | AD2: =IF($AB2="Strong Bearish","Machine pressure is strongly bearish; bearish continuation/acceptance evidence has priority.",IF($AB2="Bearish Bias","Machine leans bearish; wait for structure/timing confirmation.",IF($AB2="Strong Bullish","Machine pressure is strongly bullish; bullish expansion evidence has priority.",IF($AB2="Bullish Bias","Machine leans bullish; wait for structure/timing confirmation.","Mixed machine; wait for cleaner alignment.")))) -> Mixed machine; wait for cleaner alignment. | AE2: =NOW() -> 46182.829 | AF2: ="RealYield Δ "&TEXT($P2,"0.00")&" | NonComm Δ "&TEXT($M2,"#,##0")&" | Commercial Δ "&TEXT($J2,"#,##0")&" | OI Δ "&TEXT($G2,"#,##0") -> RealYield Δ 0.00 | NonComm Δ 2,406 | Commercial Δ -1,768 | OI Δ -17,080 | AG2: =IF($J2="","No commercial history",IF(ABS($J2)>=40000,"Major commercial shift",IF(ABS($J2)>=20000,"Large commercial shift",IF(ABS($J2)>=10000,"Moderate commercial shift","Normal commercial change")))) -> Normal commercial change | AH2: =IF($M2="","No positioning history",IF(ABS($M2)>=40000,"Major positioning shift",IF(ABS($M2)>=20000,"Large positioning shift",IF(ABS($M2)>=10000,"Moderate positioning shift","Normal positioning change")))) -> Normal positioning change | AI2: =IF(J2<=-10000,-40,IF(J2<=-5000,-25,IF(J2<=-1000,-10,IF(J2>=10000,40,IF(J2>=5000,25,IF(J2>=1000,10,0)))))) -> -10 | AJ2: =IF(M2>=10000,40,IF(M2>=5000,25,IF(M2>=1000,10,IF(M2<=-10000,-40,IF(M2<=-5000,-25,IF(M2<=-1000,-10,0)))))) -> 10 | AK2: =IF(T2="Bullish",IF(ABS(G2)>=5000,15,IF(ABS(G2)>=2000,10,IF(ABS(G2)>=500,5,0))),IF(T2="Bearish",-IF(ABS(G2)>=5000,15,IF(ABS(G2)>=2000,10,IF(ABS(G2)>=500,5,0))),0)) -> 0 | AL2: =IF(U2="Bullish",30,IF(U2="Bearish",-30,0)) -> 0 | AM2: =IF(Q2="Bullish",30,IF(Q2="Bearish",-30,0)) -> 0 | AN2: =IFERROR(SUM(MAX(AI2,0),MAX(AJ2,0),MAX(AK2,0),MAX(AL2,0),MAX(AM2,0)),0) -> 10 | AO2: =IFERROR(ABS(SUM(MIN(AI2,0),MIN(AJ2,0),MIN(AK2,0),MIN(AL2,0),MIN(AM2,0))),0) -> 10 | AP2: =MAX(0,155-IFERROR(AN2,0)-IFERROR(AO2,0)) -> 135 | AQ2: =IFERROR(AN2/155,0) -> 0.064516129 | AR2: =IFERROR(AO2/155,0) -> 0.064516129 | AS2: =IFERROR(AP2/155,0) -> 0.87096774 | AT2: =IF(AR2>=0.7,"Strong Bearish",IF(AQ2>=0.7,"Strong Bullish",IF(AR2>=0.55,"Bearish",IF(AQ2>=0.55,"Bullish",IF(AR2>=0.4,"Moderate Bearish",IF(AQ2>=0.4,"Moderate Bullish","Neutral / Mixed")))))) -> Neutral / Mixed | AU2: ="Pts → Bull "&ROUND(IFERROR(AN2,0),0)&" | Bear "&ROUND(IFERROR(AO2,0),0)&" | Neutral "&ROUND(IFERROR(AP2,0),0)&" || Commercial "&TEXT(IFERROR(J2,0),"#,##0")&" ("&IFERROR(AI2,0)&") | NonComm "&TEXT(IFERROR(M2,0),"#,##0")&" ("&IFERROR(AJ2,0)&") | OI "&TEXT(IFERROR(G2,0),"#,##0")&" ("&IFERROR(AK2,0)&") | DXY "&U2&" ("&IFERROR(AL2,0)&") | RealYield "&Q2&" ("&IFERROR(AM2,0)&")" -> Pts → Bull 10 | Bear 10 | Neutral 135 || Commercial -1,768 (-10) | NonComm 2,406 (10) | OI -17,080 (0) | DXY Neutral (0) | RealYield Neutral (0)
A3: US30 | B3: US30 | C3: =IF(COUNTIFS(CFTC_Raw!$B:$B,$B3)=0,"",MAXIFS(CFTC_Raw!$A:$A,CFTC_Raw!$B:$B,$B3)) -> 46175 | D3: =IF($C3="","",IF(COUNTIFS(CFTC_Raw!$B:$B,$B3,CFTC_Raw!$A:$A,"<"&$C3)=0,"",MAXIFS(CFTC_Raw!$A:$A,CFTC_Raw!$B:$B,$B3,CFTC_Raw!$A:$A,"<"&$C3))) -> 46168 | E3: =IF($C3="",0,SUMIFS(CFTC_Raw!$C:$C,CFTC_Raw!$B:$B,$B3,CFTC_Raw!$A:$A,$C3)) -> 77429 | F3: =IF($D3="",0,SUMIFS(CFTC_Raw!$C:$C,CFTC_Raw!$B:$B,$B3,CFTC_Raw!$A:$A,$D3)) -> 78884 | G3: =IFERROR(E3-F3,0) -> -1455 | H3: =IF($C3="",0,SUMIFS(CFTC_Raw!$D:$D,CFTC_Raw!$B:$B,$B3,CFTC_Raw!$A:$A,$C3)-SUMIFS(CFTC_Raw!$E:$E,CFTC_Raw!$B:$B,$B3,CFTC_Raw!$A:$A,$C3)) -> -14972 | I3: =IF($D3="",0,SUMIFS(CFTC_Raw!$D:$D,CFTC_Raw!$B:$B,$B3,CFTC_Raw!$A:$A,$D3)-SUMIFS(CFTC_Raw!$E:$E,CFTC_Raw!$B:$B,$B3,CFTC_Raw!$A:$A,$D3)) -> -13774 | J3: =IFERROR(H3-I3,0) -> -1198 | K3: =IF($C3="",0,SUMIFS(CFTC_Raw!$F:$F,CFTC_Raw!$B:$B,$B3,CFTC_Raw!$A:$A,$C3)-SUMIFS(CFTC_Raw!$G:$G,CFTC_Raw!$B:$B,$B3,CFTC_Raw!$A:$A,$C3)) -> 12049 | L3: =IF($D3="",0,SUMIFS(CFTC_Raw!$F:$F,CFTC_Raw!$B:$B,$B3,CFTC_Raw!$A:$A,$D3)-SUMIFS(CFTC_Raw!$G:$G,CFTC_Raw!$B:$B,$B3,CFTC_Raw!$A:$A,$D3)) -> 10110 | M3: =IFERROR(K3-L3,0) -> 1939 | N3: =IFERROR(VALUE(LOOKUP(2,1/(FRED_Raw!$B$2:$B$10000<>""),FRED_Raw!$B$2:$B$10000)),0) -> 0 | O3: {=IFERROR(VALUE(INDEX(FRED_Raw!$B$2:$B$10000,MAX(1,MATCH(2,1/(FRED_Raw!$B$2:$B$10000<>""),1)-5))),0)} -> 0 | P3: =IFERROR(VALUE(N3)-VALUE(O3),0) -> 0 | Q3: =IF(P3>0.05,"Bearish",IF(P3<-0.05,"Bullish","Neutral")) -> Neutral | R3: =IF($M3="","Neutral",IF($M3<0,"Bearish",IF($M3>0,"Bullish","Neutral"))) -> Bullish | S3: =IF($J3="","Neutral",IF($J3>10000,"Bullish",IF($J3<-10000,"Bearish","Neutral"))) -> Neutral | T3: =IF(OR($G3="",$M3=""),"Neutral",IF(AND($G3<0,$M3<0),"Bearish",IF(AND($G3>0,$M3>0),"Bullish","Neutral"))) -> Neutral | U3: {=IFERROR(XLOOKUP($A3&"|DXY",Live_Inputs!$A$2:$A$200&"|"&Live_Inputs!$B$2:$B$200,Live_Inputs!$D$2:$D$200),"Neutral")} -> Neutral | V3: =IF($U3="Bullish",1,0)+IF($Q3="Bullish",1,0)+IF($R3="Bullish",1,0)+IF($T3="Bullish",1,0) -> 1 | W3: =IF($U3="Bearish",1,0)+IF($Q3="Bearish",1,0)+IF($R3="Bearish",1,0)+IF($T3="Bearish",1,0) -> 0 | X3: =IF($U3="Neutral",1,0)+IF($Q3="Neutral",1,0)+IF($R3="Neutral",1,0)+IF($T3="Neutral",1,0) -> 3 | Y3: =IF($U3="Bullish",0.3,0)+IF($Q3="Bullish",0.3,0)+IF($R3="Bullish",0.25,0)+IF($T3="Bullish",0.15,0) -> 0.25 | Z3: =IF($U3="Bearish",0.3,0)+IF($Q3="Bearish",0.3,0)+IF($R3="Bearish",0.25,0)+IF($T3="Bearish",0.15,0) -> 0 | AA3: =IF($U3="Neutral",0.3,0)+IF($Q3="Neutral",0.3,0)+IF($R3="Neutral",0.25,0)+IF($T3="Neutral",0.15,0) -> 0.75 | AB3: =IF($Z3>=0.75,"Strong Bearish",IF($Z3>=0.55,"Bearish Bias",IF($Y3>=0.75,"Strong Bullish",IF($Y3>=0.55,"Bullish Bias","Neutral / Mixed")))) -> Neutral / Mixed | AC3: =$V3&"/4 Bullish | "&$W3&"/4 Bearish | "&$X3&"/4 Neutral" -> 1/4 Bullish | 0/4 Bearish | 3/4 Neutral | AD3: =IF($AB3="Strong Bearish","Machine pressure is strongly bearish; bearish continuation/acceptance evidence has priority.",IF($AB3="Bearish Bias","Machine leans bearish; wait for structure/timing confirmation.",IF($AB3="Strong Bullish","Machine pressure is strongly bullish; bullish expansion evidence has priority.",IF($AB3="Bullish Bias","Machine leans bullish; wait for structure/timing confirmation.","Mixed machine; wait for cleaner alignment.")))) -> Mixed machine; wait for cleaner alignment. | AE3: =NOW() -> 46182.829 | AF3: ="RealYield Δ "&TEXT($P3,"0.00")&" | NonComm Δ "&TEXT($M3,"#,##0")&" | Commercial Δ "&TEXT($J3,"#,##0")&" | OI Δ "&TEXT($G3,"#,##0") -> RealYield Δ 0.00 | NonComm Δ 1,939 | Commercial Δ -1,198 | OI Δ -1,455 | AG3: =IF($J3="","No commercial history",IF(ABS($J3)>=40000,"Major commercial shift",IF(ABS($J3)>=20000,"Large commercial shift",IF(ABS($J3)>=10000,"Moderate commercial shift","Normal commercial change")))) -> Normal commercial change | AH3: =IF($M3="","No positioning history",IF(ABS($M3)>=40000,"Major positioning shift",IF(ABS($M3)>=20000,"Large positioning shift",IF(ABS($M3)>=10000,"Moderate positioning shift","Normal positioning change")))) -> Normal positioning change | AI3: =IF(J3<=-10000,-40,IF(J3<=-5000,-25,IF(J3<=-1000,-10,IF(J3>=10000,40,IF(J3>=5000,25,IF(J3>=1000,10,0)))))) -> -10 | AJ3: =IF(M3>=10000,40,IF(M3>=5000,25,IF(M3>=1000,10,IF(M3<=-10000,-40,IF(M3<=-5000,-25,IF(M3<=-1000,-10,0)))))) -> 10 | AK3: =IF(T3="Bullish",IF(ABS(G3)>=5000,15,IF(ABS(G3)>=2000,10,IF(ABS(G3)>=500,5,0))),IF(T3="Bearish",-IF(ABS(G3)>=5000,15,IF(ABS(G3)>=2000,10,IF(ABS(G3)>=500,5,0))),0)) -> 0 | AL3: =IF(U3="Bullish",30,IF(U3="Bearish",-30,0)) -> 0 | AM3: =IF(Q3="Bullish",30,IF(Q3="Bearish",-30,0)) -> 0 | AN3: =IFERROR(SUM(MAX(AI3,0),MAX(AJ3,0),MAX(AK3,0),MAX(AL3,0),MAX(AM3,0)),0) -> 10 | AO3: =IFERROR(ABS(SUM(MIN(AI3,0),MIN(AJ3,0),MIN(AK3,0),MIN(AL3,0),MIN(AM3,0))),0) -> 10 | AP3: =MAX(0,155-IFERROR(AN3,0)-IFERROR(AO3,0)) -> 135 | AQ3: =IFERROR(AN3/155,0) -> 0.064516129 | AR3: =IFERROR(AO3/155,0) -> 0.064516129 | AS3: =IFERROR(AP3/155,0) -> 0.87096774 | AT3: =IF(AR3>=0.7,"Strong Bearish",IF(AQ3>=0.7,"Strong Bullish",IF(AR3>=0.55,"Bearish",IF(AQ3>=0.55,"Bullish",IF(AR3>=0.4,"Moderate Bearish",IF(AQ3>=0.4,"Moderate Bullish","Neutral / Mixed")))))) -> Neutral / Mixed | AU3: ="Pts → Bull "&ROUND(IFERROR(AN3,0),0)&" | Bear "&ROUND(IFERROR(AO3,0),0)&" | Neutral "&ROUND(IFERROR(AP3,0),0)&" || Commercial "&TEXT(IFERROR(J3,0),"#,##0")&" ("&IFERROR(AI3,0)&") | NonComm "&TEXT(IFERROR(M3,0),"#,##0")&" ("&IFERROR(AJ3,0)&") | OI "&TEXT(IFERROR(G3,0),"#,##0")&" ("&IFERROR(AK3,0)&") | DXY "&U3&" ("&IFERROR(AL3,0)&") | RealYield "&Q3&" ("&IFERROR(AM3,0)&")" -> Pts → Bull 10 | Bear 10 | Neutral 135 || Commercial -1,198 (-10) | NonComm 1,939 (10) | OI -1,455 (0) | DXY Neutral (0) | RealYield Neutral (0)
A4: SPX500 | B4: SPX500 | C4: =IF(COUNTIFS(CFTC_Raw!$B:$B,$B4)=0,"",MAXIFS(CFTC_Raw!$A:$A,CFTC_Raw!$B:$B,$B4)) -> 46175 | D4: =IF($C4="","",IF(COUNTIFS(CFTC_Raw!$B:$B,$B4,CFTC_Raw!$A:$A,"<"&$C4)=0,"",MAXIFS(CFTC_Raw!$A:$A,CFTC_Raw!$B:$B,$B4,CFTC_Raw!$A:$A,"<"&$C4))) -> 46168 | E4: =IF($C4="",0,SUMIFS(CFTC_Raw!$C:$C,CFTC_Raw!$B:$B,$B4,CFTC_Raw!$A:$A,$C4)) -> 2149231 | F4: =IF($D4="",0,SUMIFS(CFTC_Raw!$C:$C,CFTC_Raw!$B:$B,$B4,CFTC_Raw!$A:$A,$D4)) -> 2093621 | G4: =IFERROR(E4-F4,0) -> 55610 | H4: =IF($C4="",0,SUMIFS(CFTC_Raw!$D:$D,CFTC_Raw!$B:$B,$B4,CFTC_Raw!$A:$A,$C4)-SUMIFS(CFTC_Raw!$E:$E,CFTC_Raw!$B:$B,$B4,CFTC_Raw!$A:$A,$C4)) -> 110074 | I4: =IF($D4="",0,SUMIFS(CFTC_Raw!$D:$D,CFTC_Raw!$B:$B,$B4,CFTC_Raw!$A:$A,$D4)-SUMIFS(CFTC_Raw!$E:$E,CFTC_Raw!$B:$B,$B4,CFTC_Raw!$A:$A,$D4)) -> 54929 | J4: =IFERROR(H4-I4,0) -> 55145 | K4: =IF($C4="",0,SUMIFS(CFTC_Raw!$F:$F,CFTC_Raw!$B:$B,$B4,CFTC_Raw!$A:$A,$C4)-SUMIFS(CFTC_Raw!$G:$G,CFTC_Raw!$B:$B,$B4,CFTC_Raw!$A:$A,$C4)) -> -220768 | L4: =IF($D4="",0,SUMIFS(CFTC_Raw!$F:$F,CFTC_Raw!$B:$B,$B4,CFTC_Raw!$A:$A,$D4)-SUMIFS(CFTC_Raw!$G:$G,CFTC_Raw!$B:$B,$B4,CFTC_Raw!$A:$A,$D4)) -> -165831 | M4: =IFERROR(K4-L4,0) -> -54937 | N4: =IFERROR(VALUE(LOOKUP(2,1/(FRED_Raw!$B$2:$B$10000<>""),FRED_Raw!$B$2:$B$10000)),0) -> 0 | O4: {=IFERROR(VALUE(INDEX(FRED_Raw!$B$2:$B$10000,MAX(1,MATCH(2,1/(FRED_Raw!$B$2:$B$10000<>""),1)-5))),0)} -> 0 | P4: =IFERROR(VALUE(N4)-VALUE(O4),0) -> 0 | Q4: =IF(P4>0.05,"Bearish",IF(P4<-0.05,"Bullish","Neutral")) -> Neutral | R4: =IF($M4="","Neutral",IF($M4<0,"Bearish",IF($M4>0,"Bullish","Neutral"))) -> Bearish | S4: =IF($J4="","Neutral",IF($J4>10000,"Bullish",IF($J4<-10000,"Bearish","Neutral"))) -> Bullish | T4: =IF(OR($G4="",$M4=""),"Neutral",IF(AND($G4<0,$M4<0),"Bearish",IF(AND($G4>0,$M4>0),"Bullish","Neutral"))) -> Neutral | U4: {=IFERROR(XLOOKUP($A4&"|DXY",Live_Inputs!$A$2:$A$200&"|"&Live_Inputs!$B$2:$B$200,Live_Inputs!$D$2:$D$200),"Neutral")} -> Neutral | V4: =IF($U4="Bullish",1,0)+IF($Q4="Bullish",1,0)+IF($R4="Bullish",1,0)+IF($T4="Bullish",1,0) -> 0 | W4: =IF($U4="Bearish",1,0)+IF($Q4="Bearish",1,0)+IF($R4="Bearish",1,0)+IF($T4="Bearish",1,0) -> 1 | X4: =IF($U4="Neutral",1,0)+IF($Q4="Neutral",1,0)+IF($R4="Neutral",1,0)+IF($T4="Neutral",1,0) -> 3 | Y4: =IF($U4="Bullish",0.3,0)+IF($Q4="Bullish",0.3,0)+IF($R4="Bullish",0.25,0)+IF($T4="Bullish",0.15,0) -> 0 | Z4: =IF($U4="Bearish",0.3,0)+IF($Q4="Bearish",0.3,0)+IF($R4="Bearish",0.25,0)+IF($T4="Bearish",0.15,0) -> 0.25 | AA4: =IF($U4="Neutral",0.3,0)+IF($Q4="Neutral",0.3,0)+IF($R4="Neutral",0.25,0)+IF($T4="Neutral",0.15,0) -> 0.75 | AB4: =IF($Z4>=0.75,"Strong Bearish",IF($Z4>=0.55,"Bearish Bias",IF($Y4>=0.75,"Strong Bullish",IF($Y4>=0.55,"Bullish Bias","Neutral / Mixed")))) -> Neutral / Mixed | AC4: =$V4&"/4 Bullish | "&$W4&"/4 Bearish | "&$X4&"/4 Neutral" -> 0/4 Bullish | 1/4 Bearish | 3/4 Neutral | AD4: =IF($AB4="Strong Bearish","Machine pressure is strongly bearish; bearish continuation/acceptance evidence has priority.",IF($AB4="Bearish Bias","Machine leans bearish; wait for structure/timing confirmation.",IF($AB4="Strong Bullish","Machine pressure is strongly bullish; bullish expansion evidence has priority.",IF($AB4="Bullish Bias","Machine leans bullish; wait for structure/timing confirmation.","Mixed machine; wait for cleaner alignment.")))) -> Mixed machine; wait for cleaner alignment. | AE4: =NOW() -> 46182.829 | AF4: ="RealYield Δ "&TEXT($P4,"0.00")&" | NonComm Δ "&TEXT($M4,"#,##0")&" | Commercial Δ "&TEXT($J4,"#,##0")&" | OI Δ "&TEXT($G4,"#,##0") -> RealYield Δ 0.00 | NonComm Δ -54,937 | Commercial Δ 55,145 | OI Δ 55,610 | AG4: =IF($J4="","No commercial history",IF(ABS($J4)>=40000,"Major commercial shift",IF(ABS($J4)>=20000,"Large commercial shift",IF(ABS($J4)>=10000,"Moderate commercial shift","Normal commercial change")))) -> Major commercial shift | AH4: =IF($M4="","No positioning history",IF(ABS($M4)>=40000,"Major positioning shift",IF(ABS($M4)>=20000,"Large positioning shift",IF(ABS($M4)>=10000,"Moderate positioning shift","Normal positioning change")))) -> Major positioning shift | AI4: =IF(J4<=-10000,-40,IF(J4<=-5000,-25,IF(J4<=-1000,-10,IF(J4>=10000,40,IF(J4>=5000,25,IF(J4>=1000,10,0)))))) -> 40 | AJ4: =IF(M4>=10000,40,IF(M4>=5000,25,IF(M4>=1000,10,IF(M4<=-10000,-40,IF(M4<=-5000,-25,IF(M4<=-1000,-10,0)))))) -> -40 | AK4: =IF(T4="Bullish",IF(ABS(G4)>=5000,15,IF(ABS(G4)>=2000,10,IF(ABS(G4)>=500,5,0))),IF(T4="Bearish",-IF(ABS(G4)>=5000,15,IF(ABS(G4)>=2000,10,IF(ABS(G4)>=500,5,0))),0)) -> 0 | AL4: =IF(U4="Bullish",30,IF(U4="Bearish",-30,0)) -> 0 | AM4: =IF(Q4="Bullish",30,IF(Q4="Bearish",-30,0)) -> 0 | AN4: =IFERROR(SUM(MAX(AI4,0),MAX(AJ4,0),MAX(AK4,0),MAX(AL4,0),MAX(AM4,0)),0) -> 40 | AO4: =IFERROR(ABS(SUM(MIN(AI4,0),MIN(AJ4,0),MIN(AK4,0),MIN(AL4,0),MIN(AM4,0))),0) -> 40 | AP4: =MAX(0,155-IFERROR(AN4,0)-IFERROR(AO4,0)) -> 75 | AQ4: =IFERROR(AN4/155,0) -> 0.25806452 | AR4: =IFERROR(AO4/155,0) -> 0.25806452 | AS4: =IFERROR(AP4/155,0) -> 0.48387097 | AT4: =IF(AR4>=0.7,"Strong Bearish",IF(AQ4>=0.7,"Strong Bullish",IF(AR4>=0.55,"Bearish",IF(AQ4>=0.55,"Bullish",IF(AR4>=0.4,"Moderate Bearish",IF(AQ4>=0.4,"Moderate Bullish","Neutral / Mixed")))))) -> Neutral / Mixed | AU4: ="Pts → Bull "&ROUND(IFERROR(AN4,0),0)&" | Bear "&ROUND(IFERROR(AO4,0),0)&" | Neutral "&ROUND(IFERROR(AP4,0),0)&" || Commercial "&TEXT(IFERROR(J4,0),"#,##0")&" ("&IFERROR(AI4,0)&") | NonComm "&TEXT(IFERROR(M4,0),"#,##0")&" ("&IFERROR(AJ4,0)&") | OI "&TEXT(IFERROR(G4,0),"#,##0")&" ("&IFERROR(AK4,0)&") | DXY "&U4&" ("&IFERROR(AL4,0)&") | RealYield "&Q4&" ("&IFERROR(AM4,0)&")" -> Pts → Bull 40 | Bear 40 | Neutral 75 || Commercial 55,145 (40) | NonComm -54,937 (-40) | OI 55,610 (0) | DXY Neutral (0) | RealYield Neutral (0)
A5: NAS100 | B5: NAS100 | C5: =IF(COUNTIFS(CFTC_Raw!$B:$B,$B5)=0,"",MAXIFS(CFTC_Raw!$A:$A,CFTC_Raw!$B:$B,$B5)) -> 46175 | D5: =IF($C5="","",IF(COUNTIFS(CFTC_Raw!$B:$B,$B5,CFTC_Raw!$A:$A,"<"&$C5)=0,"",MAXIFS(CFTC_Raw!$A:$A,CFTC_Raw!$B:$B,$B5,CFTC_Raw!$A:$A,"<"&$C5))) -> 46168 | E5: =IF($C5="",0,SUMIFS(CFTC_Raw!$C:$C,CFTC_Raw!$B:$B,$B5,CFTC_Raw!$A:$A,$C5)) -> 345837 | F5: =IF($D5="",0,SUMIFS(CFTC_Raw!$C:$C,CFTC_Raw!$B:$B,$B5,CFTC_Raw!$A:$A,$D5)) -> 330617 | G5: =IFERROR(E5-F5,0) -> 15220 | H5: =IF($C5="",0,SUMIFS(CFTC_Raw!$D:$D,CFTC_Raw!$B:$B,$B5,CFTC_Raw!$A:$A,$C5)-SUMIFS(CFTC_Raw!$E:$E,CFTC_Raw!$B:$B,$B5,CFTC_Raw!$A:$A,$C5)) -> 15476 | I5: =IF($D5="",0,SUMIFS(CFTC_Raw!$D:$D,CFTC_Raw!$B:$B,$B5,CFTC_Raw!$A:$A,$D5)-SUMIFS(CFTC_Raw!$E:$E,CFTC_Raw!$B:$B,$B5,CFTC_Raw!$A:$A,$D5)) -> 174 | J5: =IFERROR(H5-I5,0) -> 15302 | K5: =IF($C5="",0,SUMIFS(CFTC_Raw!$F:$F,CFTC_Raw!$B:$B,$B5,CFTC_Raw!$A:$A,$C5)-SUMIFS(CFTC_Raw!$G:$G,CFTC_Raw!$B:$B,$B5,CFTC_Raw!$A:$A,$C5)) -> -22085 | L5: =IF($D5="",0,SUMIFS(CFTC_Raw!$F:$F,CFTC_Raw!$B:$B,$B5,CFTC_Raw!$A:$A,$D5)-SUMIFS(CFTC_Raw!$G:$G,CFTC_Raw!$B:$B,$B5,CFTC_Raw!$A:$A,$D5)) -> -11282 | M5: =IFERROR(K5-L5,0) -> -10803 | N5: =IFERROR(VALUE(LOOKUP(2,1/(FRED_Raw!$B$2:$B$10000<>""),FRED_Raw!$B$2:$B$10000)),0) -> 0 | O5: {=IFERROR(VALUE(INDEX(FRED_Raw!$B$2:$B$10000,MAX(1,MATCH(2,1/(FRED_Raw!$B$2:$B$10000<>""),1)-5))),0)} -> 0 | P5: =IFERROR(VALUE(N5)-VALUE(O5),0) -> 0 | Q5: =IF(P5>0.05,"Bearish",IF(P5<-0.05,"Bullish","Neutral")) -> Neutral | R5: =IF($M5="","Neutral",IF($M5<0,"Bearish",IF($M5>0,"Bullish","Neutral"))) -> Bearish | S5: =IF($J5="","Neutral",IF($J5>10000,"Bullish",IF($J5<-10000,"Bearish","Neutral"))) -> Bullish | T5: =IF(OR($G5="",$M5=""),"Neutral",IF(AND($G5<0,$M5<0),"Bearish",IF(AND($G5>0,$M5>0),"Bullish","Neutral"))) -> Neutral | U5: {=IFERROR(XLOOKUP($A5&"|DXY",Live_Inputs!$A$2:$A$200&"|"&Live_Inputs!$B$2:$B$200,Live_Inputs!$D$2:$D$200),"Neutral")} -> Neutral | V5: =IF($U5="Bullish",1,0)+IF($Q5="Bullish",1,0)+IF($R5="Bullish",1,0)+IF($T5="Bullish",1,0) -> 0 | W5: =IF($U5="Bearish",1,0)+IF($Q5="Bearish",1,0)+IF($R5="Bearish",1,0)+IF($T5="Bearish",1,0) -> 1 | X5: =IF($U5="Neutral",1,0)+IF($Q5="Neutral",1,0)+IF($R5="Neutral",1,0)+IF($T5="Neutral",1,0) -> 3 | Y5: =IF($U5="Bullish",0.3,0)+IF($Q5="Bullish",0.3,0)+IF($R5="Bullish",0.25,0)+IF($T5="Bullish",0.15,0) -> 0 | Z5: =IF($U5="Bearish",0.3,0)+IF($Q5="Bearish",0.3,0)+IF($R5="Bearish",0.25,0)+IF($T5="Bearish",0.15,0) -> 0.25 | AA5: =IF($U5="Neutral",0.3,0)+IF($Q5="Neutral",0.3,0)+IF($R5="Neutral",0.25,0)+IF($T5="Neutral",0.15,0) -> 0.75 | AB5: =IF($Z5>=0.75,"Strong Bearish",IF($Z5>=0.55,"Bearish Bias",IF($Y5>=0.75,"Strong Bullish",IF($Y5>=0.55,"Bullish Bias","Neutral / Mixed")))) -> Neutral / Mixed | AC5: =$V5&"/4 Bullish | "&$W5&"/4 Bearish | "&$X5&"/4 Neutral" -> 0/4 Bullish | 1/4 Bearish | 3/4 Neutral | AD5: =IF($AB5="Strong Bearish","Machine pressure is strongly bearish; bearish continuation/acceptance evidence has priority.",IF($AB5="Bearish Bias","Machine leans bearish; wait for structure/timing confirmation.",IF($AB5="Strong Bullish","Machine pressure is strongly bullish; bullish expansion evidence has priority.",IF($AB5="Bullish Bias","Machine leans bullish; wait for structure/timing confirmation.","Mixed machine; wait for cleaner alignment.")))) -> Mixed machine; wait for cleaner alignment. | AE5: =NOW() -> 46182.829 | AF5: ="RealYield Δ "&TEXT($P5,"0.00")&" | NonComm Δ "&TEXT($M5,"#,##0")&" | Commercial Δ "&TEXT($J5,"#,##0")&" | OI Δ "&TEXT($G5,"#,##0") -> RealYield Δ 0.00 | NonComm Δ -10,803 | Commercial Δ 15,302 | OI Δ 15,220 | AG5: =IF($J5="","No commercial history",IF(ABS($J5)>=40000,"Major commercial shift",IF(ABS($J5)>=20000,"Large commercial shift",IF(ABS($J5)>=10000,"Moderate commercial shift","Normal commercial change")))) -> Moderate commercial shift | AH5: =IF($M5="","No positioning history",IF(ABS($M5)>=40000,"Major positioning shift",IF(ABS($M5)>=20000,"Large positioning shift",IF(ABS($M5)>=10000,"Moderate positioning shift","Normal positioning change")))) -> Moderate positioning shift | AI5: =IF(J5<=-10000,-40,IF(J5<=-5000,-25,IF(J5<=-1000,-10,IF(J5>=10000,40,IF(J5>=5000,25,IF(J5>=1000,10,0)))))) -> 40 | AJ5: =IF(M5>=10000,40,IF(M5>=5000,25,IF(M5>=1000,10,IF(M5<=-10000,-40,IF(M5<=-5000,-25,IF(M5<=-1000,-10,0)))))) -> -40 | AK5: =IF(T5="Bullish",IF(ABS(G5)>=5000,15,IF(ABS(G5)>=2000,10,IF(ABS(G5)>=500,5,0))),IF(T5="Bearish",-IF(ABS(G5)>=5000,15,IF(ABS(G5)>=2000,10,IF(ABS(G5)>=500,5,0))),0)) -> 0 | AL5: =IF(U5="Bullish",30,IF(U5="Bearish",-30,0)) -> 0 | AM5: =IF(Q5="Bullish",30,IF(Q5="Bearish",-30,0)) -> 0 | AN5: =IFERROR(SUM(MAX(AI5,0),MAX(AJ5,0),MAX(AK5,0),MAX(AL5,0),MAX(AM5,0)),0) -> 40 | AO5: =IFERROR(ABS(SUM(MIN(AI5,0),MIN(AJ5,0),MIN(AK5,0),MIN(AL5,0),MIN(AM5,0))),0) -> 40 | AP5: =MAX(0,155-IFERROR(AN5,0)-IFERROR(AO5,0)) -> 75 | AQ5: =IFERROR(AN5/155,0) -> 0.25806452 | AR5: =IFERROR(AO5/155,0) -> 0.25806452 | AS5: =IFERROR(AP5/155,0) -> 0.48387097 | AT5: =IF(AR5>=0.7,"Strong Bearish",IF(AQ5>=0.7,"Strong Bullish",IF(AR5>=0.55,"Bearish",IF(AQ5>=0.55,"Bullish",IF(AR5>=0.4,"Moderate Bearish",IF(AQ5>=0.4,"Moderate Bullish","Neutral / Mixed")))))) -> Neutral / Mixed | AU5: ="Pts → Bull "&ROUND(IFERROR(AN5,0),0)&" | Bear "&ROUND(IFERROR(AO5,0),0)&" | Neutral "&ROUND(IFERROR(AP5,0),0)&" || Commercial "&TEXT(IFERROR(J5,0),"#,##0")&" ("&IFERROR(AI5,0)&") | NonComm "&TEXT(IFERROR(M5,0),"#,##0")&" ("&IFERROR(AJ5,0)&") | OI "&TEXT(IFERROR(G5,0),"#,##0")&" ("&IFERROR(AK5,0)&") | DXY "&U5&" ("&IFERROR(AL5,0)&") | RealYield "&Q5&" ("&IFERROR(AM5,0)&")" -> Pts → Bull 40 | Bear 40 | Neutral 75 || Commercial 15,302 (40) | NonComm -10,803 (-40) | OI 15,220 (0) | DXY Neutral (0) | RealYield Neutral (0)
A6: Custom | B6: Custom | C6: =IF(COUNTIFS(CFTC_Raw!$B:$B,$B6)=0,"",MAXIFS(CFTC_Raw!$A:$A,CFTC_Raw!$B:$B,$B6)) | D6: =IF($C6="","",IF(COUNTIFS(CFTC_Raw!$B:$B,$B6,CFTC_Raw!$A:$A,"<"&$C6)=0,"",MAXIFS(CFTC_Raw!$A:$A,CFTC_Raw!$B:$B,$B6,CFTC_Raw!$A:$A,"<"&$C6))) | E6: =IF($C6="",0,SUMIFS(CFTC_Raw!$C:$C,CFTC_Raw!$B:$B,$B6,CFTC_Raw!$A:$A,$C6)) -> 0 | F6: =IF($D6="",0,SUMIFS(CFTC_Raw!$C:$C,CFTC_Raw!$B:$B,$B6,CFTC_Raw!$A:$A,$D6)) -> 0 | G6: =IFERROR(E6-F6,0) -> 0 | H6: =IF($C6="",0,SUMIFS(CFTC_Raw!$D:$D,CFTC_Raw!$B:$B,$B6,CFTC_Raw!$A:$A,$C6)-SUMIFS(CFTC_Raw!$E:$E,CFTC_Raw!$B:$B,$B6,CFTC_Raw!$A:$A,$C6)) -> 0 | I6: =IF($D6="",0,SUMIFS(CFTC_Raw!$D:$D,CFTC_Raw!$B:$B,$B6,CFTC_Raw!$A:$A,$D6)-SUMIFS(CFTC_Raw!$E:$E,CFTC_Raw!$B:$B,$B6,CFTC_Raw!$A:$A,$D6)) -> 0 | J6: =IFERROR(H6-I6,0) -> 0 | K6: =IF($C6="",0,SUMIFS(CFTC_Raw!$F:$F,CFTC_Raw!$B:$B,$B6,CFTC_Raw!$A:$A,$C6)-SUMIFS(CFTC_Raw!$G:$G,CFTC_Raw!$B:$B,$B6,CFTC_Raw!$A:$A,$C6)) -> 0 | L6: =IF($D6="",0,SUMIFS(CFTC_Raw!$F:$F,CFTC_Raw!$B:$B,$B6,CFTC_Raw!$A:$A,$D6)-SUMIFS(CFTC_Raw!$G:$G,CFTC_Raw!$B:$B,$B6,CFTC_Raw!$A:$A,$D6)) -> 0 | M6: =IFERROR(K6-L6,0) -> 0 | N6: =IFERROR(VALUE(LOOKUP(2,1/(FRED_Raw!$B$2:$B$10000<>""),FRED_Raw!$B$2:$B$10000)),0) -> 0 | O6: {=IFERROR(VALUE(INDEX(FRED_Raw!$B$2:$B$10000,MAX(1,MATCH(2,1/(FRED_Raw!$B$2:$B$10000<>""),1)-5))),0)} -> 0 | P6: =IFERROR(VALUE(N6)-VALUE(O6),0) -> 0 | Q6: =IF(P6>0.05,"Bearish",IF(P6<-0.05,"Bullish","Neutral")) -> Neutral | R6: =IF($M6="","Neutral",IF($M6<0,"Bearish",IF($M6>0,"Bullish","Neutral"))) -> Neutral | S6: =IF($J6="","Neutral",IF($J6>10000,"Bullish",IF($J6<-10000,"Bearish","Neutral"))) -> Neutral | T6: =IF(OR($G6="",$M6=""),"Neutral",IF(AND($G6<0,$M6<0),"Bearish",IF(AND($G6>0,$M6>0),"Bullish","Neutral"))) -> Neutral | U6: {=IFERROR(XLOOKUP($A6&"|DXY",Live_Inputs!$A$2:$A$200&"|"&Live_Inputs!$B$2:$B$200,Live_Inputs!$D$2:$D$200),"Neutral")} -> Neutral | V6: =IF($U6="Bullish",1,0)+IF($Q6="Bullish",1,0)+IF($R6="Bullish",1,0)+IF($T6="Bullish",1,0) -> 0 | W6: =IF($U6="Bearish",1,0)+IF($Q6="Bearish",1,0)+IF($R6="Bearish",1,0)+IF($T6="Bearish",1,0) -> 0 | X6: =IF($U6="Neutral",1,0)+IF($Q6="Neutral",1,0)+IF($R6="Neutral",1,0)+IF($T6="Neutral",1,0) -> 4 | Y6: =IF($U6="Bullish",0.3,0)+IF($Q6="Bullish",0.3,0)+IF($R6="Bullish",0.25,0)+IF($T6="Bullish",0.15,0) -> 0 | Z6: =IF($U6="Bearish",0.3,0)+IF($Q6="Bearish",0.3,0)+IF($R6="Bearish",0.25,0)+IF($T6="Bearish",0.15,0) -> 0 | AA6: =IF($U6="Neutral",0.3,0)+IF($Q6="Neutral",0.3,0)+IF($R6="Neutral",0.25,0)+IF($T6="Neutral",0.15,0) -> 1 | AB6: =IF($Z6>=0.75,"Strong Bearish",IF($Z6>=0.55,"Bearish Bias",IF($Y6>=0.75,"Strong Bullish",IF($Y6>=0.55,"Bullish Bias","Neutral / Mixed")))) -> Neutral / Mixed | AC6: =$V6&"/4 Bullish | "&$W6&"/4 Bearish | "&$X6&"/4 Neutral" -> 0/4 Bullish | 0/4 Bearish | 4/4 Neutral | AD6: =IF($AB6="Strong Bearish","Machine pressure is strongly bearish; bearish continuation/acceptance evidence has priority.",IF($AB6="Bearish Bias","Machine leans bearish; wait for structure/timing confirmation.",IF($AB6="Strong Bullish","Machine pressure is strongly bullish; bullish expansion evidence has priority.",IF($AB6="Bullish Bias","Machine leans bullish; wait for structure/timing confirmation.","Mixed machine; wait for cleaner alignment.")))) -> Mixed machine; wait for cleaner alignment. | AE6: =NOW() -> 46182.829 | AF6: ="RealYield Δ "&TEXT($P6,"0.00")&" | NonComm Δ "&TEXT($M6,"#,##0")&" | Commercial Δ "&TEXT($J6,"#,##0")&" | OI Δ "&TEXT($G6,"#,##0") -> RealYield Δ 0.00 | NonComm Δ 0 | Commercial Δ 0 | OI Δ 0 | AG6: =IF($J6="","No commercial history",IF(ABS($J6)>=40000,"Major commercial shift",IF(ABS($J6)>=20000,"Large commercial shift",IF(ABS($J6)>=10000,"Moderate commercial shift","Normal commercial change")))) -> Normal commercial change | AH6: =IF($M6="","No positioning history",IF(ABS($M6)>=40000,"Major positioning shift",IF(ABS($M6)>=20000,"Large positioning shift",IF(ABS($M6)>=10000,"Moderate positioning shift","Normal positioning change")))) -> Normal positioning change | AI6: =IF(J6<=-10000,-40,IF(J6<=-5000,-25,IF(J6<=-1000,-10,IF(J6>=10000,40,IF(J6>=5000,25,IF(J6>=1000,10,0)))))) -> 0 | AJ6: =IF(M6>=10000,40,IF(M6>=5000,25,IF(M6>=1000,10,IF(M6<=-10000,-40,IF(M6<=-5000,-25,IF(M6<=-1000,-10,0)))))) -> 0 | AK6: =IF(T6="Bullish",IF(ABS(G6)>=5000,15,IF(ABS(G6)>=2000,10,IF(ABS(G6)>=500,5,0))),IF(T6="Bearish",-IF(ABS(G6)>=5000,15,IF(ABS(G6)>=2000,10,IF(ABS(G6)>=500,5,0))),0)) -> 0 | AL6: =IF(U6="Bullish",30,IF(U6="Bearish",-30,0)) -> 0 | AM6: =IF(Q6="Bullish",30,IF(Q6="Bearish",-30,0)) -> 0 | AN6: =IFERROR(SUM(MAX(AI6,0),MAX(AJ6,0),MAX(AK6,0),MAX(AL6,0),MAX(AM6,0)),0) -> 0 | AO6: =IFERROR(ABS(SUM(MIN(AI6,0),MIN(AJ6,0),MIN(AK6,0),MIN(AL6,0),MIN(AM6,0))),0) -> 0 | AP6: =MAX(0,155-IFERROR(AN6,0)-IFERROR(AO6,0)) -> 155 | AQ6: =IFERROR(AN6/155,0) -> 0 | AR6: =IFERROR(AO6/155,0) -> 0 | AS6: =IFERROR(AP6/155,0) -> 1 | AT6: =IF(AR6>=0.7,"Strong Bearish",IF(AQ6>=0.7,"Strong Bullish",IF(AR6>=0.55,"Bearish",IF(AQ6>=0.55,"Bullish",IF(AR6>=0.4,"Moderate Bearish",IF(AQ6>=0.4,"Moderate Bullish","Neutral / Mixed")))))) -> Neutral / Mixed | AU6: ="Pts → Bull "&ROUND(IFERROR(AN6,0),0)&" | Bear "&ROUND(IFERROR(AO6,0),0)&" | Neutral "&ROUND(IFERROR(AP6,0),0)&" || Commercial "&TEXT(IFERROR(J6,0),"#,##0")&" ("&IFERROR(AI6,0)&") | NonComm "&TEXT(IFERROR(M6,0),"#,##0")&" ("&IFERROR(AJ6,0)&") | OI "&TEXT(IFERROR(G6,0),"#,##0")&" ("&IFERROR(AK6,0)&") | DXY "&U6&" ("&IFERROR(AL6,0)&") | RealYield "&Q6&" ("&IFERROR(AM6,0)&")" -> Pts → Bull 0 | Bear 0 | Neutral 155 || Commercial 0 (0) | NonComm 0 (0) | OI 0 (0) | DXY Neutral (0) | RealYield Neutral (0)

Sheet Timing_Calibration
A1: Weekly Timing by Asset + Machine State
A2: Asset | B2: State | C2: Weeks | D2: TopHighDay | E2: HighDayPct | F2: TopLowDay | G2: LowDayPct | H2: TopHighHourET | I2: HighHourPct | J2: TopLowHourET | K2: LowHourPct | L2: EarlyHighSunTuePct | M2: EarlyLowSunTuePct | N2: HighBeforeLowPct
A3: US30_CFD | B3: All | C3: 179 | D3: Friday | E3: 35.8 | F3: Friday | G3: 26.3 | H3: 9 | I3: 15.6 | J3: 9 | K3: 14.5 | L3: 34.1 | M3: 44.1 | N3: 43
A4: US30_CFD | B4: BullishWeeks | C4: 104 | D4: Friday | E4: 58.7 | F4: Monday | G4: 33.7 | H4: 10 | I4: 16.3 | J4: 9 | K4: 15.4 | L4: 7.7 | M4: 64.4 | N4: 12.5
A5: US30_CFD | B5: BearishWeeks | C5: 75 | D5: Monday | E5: 40 | F5: Friday | G5: 54.7 | H5: 9 | I5: 22.7 | J5: 9 | K5: 13.3 | L5: 70.7 | M5: 16 | N5: 85.3
A6: US30_CFD | B6: ExpansionWeeks | C6: 83 | D6: Friday | E6: 36.1 | F6: Friday | G6: 31.3 | H6: 12 | I6: 12 | J6: 9 | K6: 9.6 | L6: 37.3 | M6: 44.6 | N6: 45.8
A7: SPX | B7: All | C7: 596 | D7: Friday | E7: 38.1 | F7: Monday | G7: 30.4 | H7: 9 | I7: 35.6 | J7: 9 | K7: 34.4 | L7: 30.7 | M7: 47.1 | N7: 42.6
A8: SPX | B8: BullishWeeks | C8: 352 | D8: Friday | E8: 61.6 | F8: Monday | G8: 49.4 | H8: 15 | I8: 27.3 | J8: 9 | K8: 44.9 | L8: 6.8 | M8: 71.9 | N8: 9.7
A9: SPX | B9: BearishWeeks | C9: 244 | D9: Monday | E9: 38.1 | F9: Friday | G9: 53.7 | H9: 9 | I9: 49.6 | J9: 15 | K9: 22.1 | L9: 65.2 | M9: 11.5 | N9: 90.2
A10: SPX | B10: ExpansionWeeks | C10: 284 | D10: Friday | E10: 35.6 | F10: Monday | G10: 33.8 | H10: 9 | I10: 37.7 | J10: 9 | K10: 32 | L10: 37 | M10: 44.7 | N10: 47.5
A11: VIX | B11: All | C11: 336 | D11: Monday | E11: 31.5 | F11: Friday | G11: 40.2 | H11: 3 | I11: 14.6 | J11: 15 | K11: 23.5 | L11: 48.5 | M11: 27.1 | N11: 59.5
A12: VIX | B12: BullishWeeks | C12: 110 | D12: Friday | E12: 62.7 | F12: Monday | G12: 40 | H12: 15 | I12: 20 | J12: 9 | K12: 16.4 | L12: 3.6 | M12: 60.9 | N12: 6.4
A13: VIX | B13: BearishWeeks | C13: 226 | D13: Monday | E13: 46.5 | F13: Friday | G13: 57.1 | H13: 3 | I13: 17.7 | J13: 15 | K13: 30.1 | L13: 70.4 | M13: 10.6 | N13: 85.4
A14: VIX | B14: ExpansionWeeks | C14: 160 | D14: Monday | E14: 31.9 | F14: Friday | G14: 34.4 | H14: 3 | I14: 14.4 | J14: 15 | K14: 26.2 | L14: 43.8 | M14: 36.9 | N14: 51.2
... A34: NDX | B34: ExpansionWeeks | C34: 291 | D34: Friday | E34: 36.8 | F34: Monday | G34: 35.4 | H34: 9 | I34: 40.2 | J34: 9 | K34: 38.8 | L34: 36.4 | M34: 47.8 | N34: 46.4

Sheet Calendar_Alerts
A1: Calendar-Style Alerts to Add
A2: Alert Name | B2: Time Window | C2: Applies When | D2: Action Note
A3: Weekly Open | B3: Sunday 18:00 ET | C3: All | D3: Check gap direction, gap size, first impulse, and Machine read. Do not chase first print.
A4: Early Week High Window | B4: Monday 08:30–10:30 ET | C4: Bearish Silver / Bearish US30 | D4: Primary watch for weekly high/liquidity pop. Require structure rejection and Machine confirmation.
A5: Early Week High Window | B5: Tuesday 08:30–10:30 ET | C5: Bearish Silver / Bearish US30 | D5: Secondary high window. If Monday did not form high, Tuesday becomes priority.
A6: Bullish Weekly Low Window | B6: Sunday 18:00–23:00 ET | C6: Bullish Silver / Bullish Risk | D6: Silver bullish weeks often form low Sunday evening; use only if machine aligns bullish.
A7: Bullish Weekly Low Window | B7: Monday 09:00–10:30 ET | C7: Bullish US30/SPX/NDX | D7: Index bullish weeks often form low Monday 9 AM ET area.
A8: Thursday Reversal Watch | B8: Thursday 09:00–15:30 ET | C8: Mixed / late-week liquidity | D8: Watch for weekly extreme and Friday reversal/terminal behavior.
A9: Friday Terminal Extreme | B9: Friday 09:00–15:30 ET | C9: Trend continuation weeks | D9: Bearish weeks often print terminal low Friday; bullish weeks often print terminal high Friday.

Sheet Calibration_Data_Coverage
A1: Dataset Coverage
A2: Asset | B2: Rows | C2: Start | D2: End | E2: Weeks | F2: MedianWeeklyRangePct | G2: AvgWeeklyRangePct
A3: US30_CFD | B3: 20554 | C3: 2023-01-02 18:00:00-05:00 | D3: 2026-06-07 23:00:00-04:00 | E3: 179 | F3: 2.58 | G3: 2.76
A4: SPX | B4: 20052 | C4: 2015-01-02 09:30:00-05:00 | D4: 2026-06-05 15:30:00-04:00 | E4: 596 | F4: 2.35 | G4: 2.87
A5: VIX | B5: 21805 | C5: 2020-01-02 03:15:00-05:00 | D5: 2026-06-05 15:30:00-04:00 | E5: 336 | F5: 20.18 | G5: 25.08
A6: DJI | B6: 20054 | C6: 2015-01-02 09:30:00-05:00 | D6: 2026-06-05 15:30:00-04:00 | E6: 596 | F6: 2.38 | G6: 2.8
A7: SI_COMEX | B7: 20263 | C7: 2023-01-02 18:00:00-05:00 | D7: 2026-06-07 23:00:00-04:00 | E7: 179 | F7: 6.21 | G7: 7.71
A8: XAGUSD_SPOT | B8: 20267 | C8: 2023-01-02 18:00:00-05:00 | D8: 2026-06-07 23:00:00-04:00 | E8: 179 | F8: 5.99 | G8: 7.56
A9: GOLD | B9: 20275 | C9: 2023-01-02 18:00:00-05:00 | D9: 2026-06-07 23:00:00-04:00 | E9: 179 | F9: 3.18 | G9: 3.79
A10: NDX | B10: 20044 | C10: 2015-01-02 09:30:00-05:00 | D10: 2026-06-05 15:30:00-04:00 | E10: 596 | F10: 3.34 | G10: 3.77

Sheet Lead_Lag
A1: Lead/Lag and Correlation
A2: Pair | B2: Rows | C2: SameHourCorr | D2: BestLagHours_A_leads_B | E2: BestLagCorr | F2: Beta_B_on_A
A3: SI_COMEX vs XAGUSD_SPOT | B3: 20221 | C3: 0.9841 | D3: 0 | E3: 0.9841 | F3: 0.977
A4: GOLD vs XAGUSD_SPOT | B4: 20233 | C4: 0.7593 | D4: 0 | E4: 0.7593 | F4: 1.614

Sheet Gap_Behavior
A1: Sunday / Week-Opening Gap Behavior
A2: Asset | B2: GapWeeks | C2: MedianAbsGapPct | D2: GapFillRatePct | E2: BigGapWeeks_gt005pct | F2: BigGapFillRatePct | G2: DownGapPct
A3: US30_CFD | B3: 178 | C3: 0.089 | D3: 94.9 | E3: 123 | F3: 92.7 | G3: 37.1
A4: SPX | B4: 595 | C4: 0.225 | D4: 78.2 | E4: 515 | F4: 75 | G4: 46.1
A5: VIX | B5: 335 | C5: 4.398 | D5: 82.4 | E5: 330 | F5: 82.1 | G5: 14.6
A6: DJI | B6: 595 | C6: 0.172 | D6: 77.8 | E6: 474 | F6: 73.6 | G6: 45.9
A7: SI_COMEX | B7: 178 | C7: 0.091 | D7: 93.8 | E7: 114 | F7: 90.4 | G7: 39.9
A8: XAGUSD_SPOT | B8: 178 | C8: 0 | D8: 97.2 | E8: 40 | F8: 90 | G8: 28.7
A9: GOLD | B9: 178 | C9: 0.045 | D9: 93.8 | E9: 84 | F9: 91.7 | G9: 43.8
A10: NDX | B10: 595 | C10: 0.404 | D10: 78.3 | E10: 553 | F10: 76.9 | G10: 45

Sheet Expansion_Profile
A1: Expansion vs Consolidation Behavior
A2: Asset | B2: ExpansionWeeks | C2: ExpansionPct | D2: AfterExpansionNextWeekSameDirectionPct | E2: AfterExpansionNextWeekAvgRetPct | F2: AfterExpansionNextWeekAvgRangePct | G2: MedianRangePct
A3: US30_CFD | B3: 83 | C3: 46.4 | D3: 59 | E3: 0.54 | F3: 2.95 | G3: 2.58
A4: SPX | B4: 284 | C4: 47.7 | D4: 49.6 | E4: 0.35 | F4: 3.42 | G4: 2.35
A5: VIX | B5: 160 | C5: 47.6 | D5: 51.2 | E5: -4.19 | F5: 27.42 | G5: 20.18
A6: DJI | B6: 282 | C6: 47.3 | D6: 48.9 | E6: 0.28 | F6: 3.24 | G6: 2.38
A7: SI_COMEX | B7: 84 | C7: 46.9 | D7: 51.2 | E7: 1.09 | F7: 8.59 | G7: 6.21
A8: XAGUSD_SPOT | B8: 85 | C8: 47.5 | D8: 49.4 | E8: 1.6 | F8: 8.42 | G8: 5.99
A9: GOLD | B9: 85 | C9: 47.5 | D9: 54.1 | E9: 0.69 | F9: 4.37 | G9: 3.18
A10: NDX | B10: 291 | C10: 48.8 | D10: 51.5 | E10: 0.62 | F10: 4.33 | G10: 3.34

Sheet Sequence_Stats
A1: High-to-Low / Low-to-High Sequencing
A2: Asset | B2: EarlyHighSunTuePct | C2: EarlyLowSunTuePct | D2: HighBeforeLowPct | E2: LowBeforeHighPct
A3: US30_CFD | B3: 34.1 | C3: 44.1 | D3: 43 | E3: 57
A4: SPX | B4: 30.7 | C4: 47.1 | D4: 42.6 | E4: 57.4
A5: VIX | B5: 48.5 | C5: 27.1 | D5: 59.5 | E5: 40.5
A6: DJI | B6: 36.1 | C6: 46.1 | D6: 45.6 | E6: 54.4
A7: SI_COMEX | B7: 36.3 | C7: 50.3 | D7: 46.4 | E7: 53.6
A8: XAGUSD_SPOT | B8: 35.8 | C8: 52.5 | D8: 44.7 | E8: 55.3
A9: GOLD | B9: 35.8 | C9: 59.2 | D9: 40.2 | E9: 59.8
A10: NDX | B10: 33.1 | C10: 50.7 | D10: 42.6 | E10: 57.4

Sheet Machine_Update_Block
A1: Copy/Integrate These Rules Into Timing + Calendar Layers
A2: Asset/Layer | B2: Machine State | C2: Timing Rule | D2: Calendar Alert | E2: Machine Integration Note
A3: XAGUSD / Silver | B3: Bearish machine | C3: Weekly high window: Sunday–Tuesday; top day Monday in spot, Sunday in SI. Primary high hour: 9 AM ET. | D3: Weekly low tends to form Friday. Watch 9 AM ET for high/low extremes. | E3: Use early-week rally/liquidity pop as sell-confirmation only if Machine remains bearish and structure rejects.
A4: XAGUSD / Silver | B4: Bullish machine | C4: Weekly low window: Sunday–Tuesday; top low day Sunday. Primary low hour: 6 PM ET / 18 ET. | D4: Weekly high tends to form Friday. 9 AM ET is still the main high-hour. | E4: If weekly low is formed early and Machine flips bullish, continuation into Friday is the dominant template.
A5: US30 CFD | B5: Bearish machine | C5: Weekly high window: Sunday–Tuesday; top high day Monday. Top high hour: 9 AM ET. | D5: Weekly low tends to form Friday. Watch 9 AM ET and late day for terminal low. | E5: This matches your “early-week high → Friday low” bearish tape. Calendar alert should fire Sunday evening through Tuesday 11 AM ET.
A6: US30 CFD | B6: Bullish machine | C6: Weekly low window: Sunday–Tuesday; top low day Monday. Top low hour: 9 AM ET. | D6: Weekly high tends to form Friday. Top high hour: 10 AM ET. | E6: If Monday sells down into structure while Machine bullish, treat as likely weekly low candidate.
A7: SPX / DJI / NDX | B7: Bearish machine | C7: Bearish weeks overwhelmingly make highs Monday and lows Friday. | D7: 9 AM ET is the dominant high/low hour across cash indices. | E7: Use as confirmation/proxy layer for US30, not a replacement for US30 CFD behavior.
A8: VIX | B8: Risk confirmation | C8: VIX bearish weeks often high Monday and low Friday; VIX bullish weeks high Friday and low Monday. | D8: VIX should move opposite risk indices; same-hour correlation to SPX/US30 is negative. | E8: Use VIX as a risk-flow confirmation, not a direct entry trigger.

Sheet Briefing
A1: MARKET MACHINE BRIEFING v4.7 — WEATHER RADAR FRONT PAGE
A2: Compact decision-support briefing: machine environment → primary conflict → timing window → dashboard drill-down. Not a trade signal.
A4: Selected Asset | B4: =Dashboard!B4 -> XAGUSD | D4: Machine State Used | E4: =IF(ISNUMBER(SEARCH("Bearish",B6)),"Bearish",IF(ISNUMBER(SEARCH("Bullish",B6)),"Bullish","Neutral")) -> Neutral | G4: Last Refresh | H4: =IFERROR(Health_Check!B4,"") -> 0
A6: Current Environment | B6: {=IFERROR(INDEX(Signal_Engine!$AT:$AT,MATCH($B$4,Signal_Engine!$A:$A,0)),"")} -> Neutral / Mixed | D6: Conviction | E6: {=IFERROR(ROUND(MAX(INDEX(Signal_Engine!$AQ:$AQ,MATCH($B$4,Signal_Engine!$A:$A,0)),INDEX(Signal_Engine!$AR:$AR,MATCH($B$4,Signal_Engine!$A:$A,0)))*100,0)&"/100","")} -> 6/100 | G6: Historical Alignment | H6: {=IFERROR(ROUND((MAX(INDEX(Signal_Engine!$AQ:$AQ,MATCH($B$4,Signal_Engine!$A:$A,0)),INDEX(Signal_Engine!$AR:$AR,MATCH($B$4,Signal_Engine!$A:$A,0)))*0.55+IF(INDEX(Timing!$H:$H,SUMPRODUCT((Timing!$A$2:$A$17=$B$4)*(Timing!$B$2:$B$17=$E$4)*ROW(Timing!$H$2:$H$17)))="High",0.25,IF(INDEX(Timing!$H:$H,SUMPRODUCT((Timing!$A$2:$A$17=$B$4)*(Timing!$B$2:$B$17=$E$4)*ROW(Timing!$H$2:$H$17)))="Moderate-High",0.18,0.1))+IF(INDEX(Seasonality!$E:$E,SUMPRODUCT((Seasonality!$A$2:$A$200=$B$4)*(Seasonality!$B$2:$B$200=TEXT(TODAY(),"mmmm"))*ROW(Seasonality!$E$2:$E$200)))="Strong",0.2,IF(INDEX(Seasonality!$E:$E,SUMPRODUCT((Seasonality!$A$2:$A$200=$B$4)*(Seasonality!$B$2:$B$200=TEXT(TODAY(),"mmmm"))*ROW(Seasonality!$E$2:$E$200)))="Moderate",0.12,0.05)))*100,0)&"%","Needs data")} -> 49%
A8: Primary Conflict | B8: {=IFERROR(IF(AND(INDEX(Signal_Engine!$AI:$AI,MATCH($B$4,Signal_Engine!$A:$A,0))<0,INDEX(Signal_Engine!$AM:$AM,MATCH($B$4,Signal_Engine!$A:$A,0))<0),"Commercial liquidation + rising real-yield pressure",IF(AND(INDEX(Signal_Engine!$AI:$AI,MATCH($B$4,Signal_Engine!$A:$A,0))>0,INDEX(Signal_Engine!$AM:$AM,MATCH($B$4,Signal_Engine!$A:$A,0))>0),"Commercial accumulation + falling real-yield relief",IF(AND(INDEX(Signal_Engine!$AI:$AI,MATCH($B$4,Signal_Engine!$A:$A,0))>0,INDEX(Signal_Engine!$AM:$AM,MATCH($B$4,Signal_Engine!$A:$A,0))<0),"Commercial accumulation vs rising real-yield pressure",IF(AND(INDEX(Signal_Engine!$AI:$AI,MATCH($B$4,Signal_Engine!$A:$A,0))<0,INDEX(Signal_Engine!$AM:$AM,MATCH($B$4,Signal_Engine!$A:$A,0))>0),"Commercial liquidation vs falling real-yield relief","Mixed crosscurrents / no dominant conflict")))),"")} -> Mixed crosscurrents / no dominant conflict
A10: Highest Probability Window | B10: {=IFERROR("Weekly High: "&INDEX(Timing!$C:$C,SUMPRODUCT((Timing!$A$2:$A$17=$B$4)*(Timing!$B$2:$B$17=$E$4)*ROW(Timing!$C$2:$C$17)))&" | Weekly Low: "&INDEX(Timing!$D:$D,SUMPRODUCT((Timing!$A$2:$A$17=$B$4)*(Timing!$B$2:$B$17=$E$4)*ROW(Timing!$D$2:$D$17)))&" | Primary: "&INDEX(Timing!$E:$E,SUMPRODUCT((Timing!$A$2:$A$17=$B$4)*(Timing!$B$2:$B$17=$E$4)*ROW(Timing!$E$2:$E$17))),"Timing data pending")} -> Weekly High: Friday (35.8%) | Sun–Tue high 35.8% | Weekly Low: Sunday (20.7%) | Sun–Tue low 52.5% | Primary: High 09:00 ET (15.1%) / Low 18:00 ET (18.4%)
A12: Operational Note | B12: {=IFERROR(INDEX(Signal_Engine!$AD:$AD,MATCH($B$4,Signal_Engine!$A:$A,0))&" "&INDEX(Timing!$G:$G,SUMPRODUCT((Timing!$A$2:$A$17=$B$4)*(Timing!$B$2:$B$17=$E$4)*ROW(Timing!$G$2:$G$17))),"Check dashboard tabs for details.")} -> Mixed machine; wait for cleaner alignment. Baseline mixed-machine timing. Use as reference only; high-before-low 44.7%.
A15: EVIDENCE STACK
A16: Layer | B16: Status / Value | C16: Score / Weight | D16: Interpretation | E16: Source / Drill-Down | G16: ="MARKET MACHINE BRIEFING — "&$B$4&CHAR(10)&"Environment: "&$B$6&" | Conviction: "&$E$6&" | Alignment: "&$H$6&CHAR(10)&"Primary conflict: "&$B$8&CHAR(10)&"Window: "&$B$10&CHAR(10)&"Note: "&$B$12 -> MARKET MACHINE BRIEFING — XAGUSD Environment: Neutral / Mixed | Conviction: 6/100 | Alignment: 49% Primary conflict: Mixed crosscurrents / no dominant conflict Window: Weekly High: Friday (35.8%) | Sun–Tue high 35.8% | Weekly Low: Sunday (20.7%) | Sun–Tue low 52.5% | Primary: High 09:00 ET (15.1%) / Low 18:00 ET (18.4%) Note: Mixed machine; wait for cleaner alignment. Baseline mixed-machine timing. Use as reference only; high-before-low 44.7%.
A17: DXY | B17: {=IFERROR(INDEX(Signal_Engine!$U:$U,MATCH($B$4,Signal_Engine!$A:$A,0)),"")} -> Neutral | C17: {=IFERROR(INDEX(Signal_Engine!$AL:$AL,MATCH($B$4,Signal_Engine!$A:$A,0)),"")} -> 0 | D17: Dollar pressure / relief | E17: Signal_Engine
A18: Real Yields | B18: {=IFERROR(INDEX(Signal_Engine!$Q:$Q,MATCH($B$4,Signal_Engine!$A:$A,0)),"")} -> Neutral | C18: {=IFERROR(INDEX(Signal_Engine!$AM:$AM,MATCH($B$4,Signal_Engine!$A:$A,0)),"")} -> 0 | D18: Discount-rate pressure | E18: FRED_Raw → Signal_Engine
A19: Commercials | B19: {=IFERROR(INDEX(Signal_Engine!$S:$S,MATCH($B$4,Signal_Engine!$A:$A,0)),"")} -> Neutral | C19: {=IFERROR(INDEX(Signal_Engine!$AI:$AI,MATCH($B$4,Signal_Engine!$A:$A,0)),"")} -> -10 | D19: Commercial net change | E19: CFTC_Raw → Signal_Engine
A20: Managed Money | B20: {=IFERROR(INDEX(Signal_Engine!$R:$R,MATCH($B$4,Signal_Engine!$A:$A,0)),"")} -> Bullish | C20: {=IFERROR(INDEX(Signal_Engine!$AJ:$AJ,MATCH($B$4,Signal_Engine!$A:$A,0)),"")} -> 10 | D20: Noncommercial positioning | E20: CFTC_Raw → Signal_Engine
A21: Open Interest | B21: {=IFERROR(INDEX(Signal_Engine!$T:$T,MATCH($B$4,Signal_Engine!$A:$A,0)),"")} -> Neutral | C21: {=IFERROR(INDEX(Signal_Engine!$AK:$AK,MATCH($B$4,Signal_Engine!$A:$A,0)),"")} -> 0 | D21: Participation / conviction | E21: CFTC_Raw → Signal_Engine
A22: Seasonality | B22: {=IFERROR(INDEX(Seasonality!$D:$D,SUMPRODUCT((Seasonality!$A$2:$A$200=$B$4)*(Seasonality!$B$2:$B$200=TEXT(TODAY(),"mmmm"))*ROW(Seasonality!$D$2:$D$200))),"")} -> Bearish | C22: {=IFERROR(INDEX(Seasonality!$E:$E,SUMPRODUCT((Seasonality!$A$2:$A$200=$B$4)*(Seasonality!$B$2:$B$200=TEXT(TODAY(),"mmmm"))*ROW(Seasonality!$E$2:$E$200))),"")} -> Strong | D22: Calendar tendency | E22: Seasonality
A23: Timing | B23: {=IFERROR(INDEX(Timing!$H:$H,SUMPRODUCT((Timing!$A$2:$A$17=$B$4)*(Timing!$B$2:$B$17=$E$4)*ROW(Timing!$H$2:$H$17))),"")} -> High | C23: {=IFERROR(INDEX(Timing!$E:$E,SUMPRODUCT((Timing!$A$2:$A$17=$B$4)*(Timing!$B$2:$B$17=$E$4)*ROW(Timing!$E$2:$E$17))),"")} -> High 09:00 ET (15.1%) / Low 18:00 ET (18.4%) | D23: Highest probability hours/windows | E23: Timing

Sheet Health_Check
A1: MARKET MACHINE HEALTH CHECK
A3: Component | B3: Last Update / Latest Date | C3: Status | D3: Expected Cadence | E3: Source Tab | F3: Failure Meaning | G3: Next Action | H3: Owner
A4: FRED Feed | B4: =IFERROR(MAX(FRED_Raw!$E:$E),"") -> 0 | C4: =IF(B4<>"","PASS","REVIEW") -> PASS | D4: Daily / market days | E4: FRED_Raw | F4: Yield feed not updated | G4: Run refreshFRED() | H4: System
A5: CFTC Feed | B5: =IFERROR(MAX(CFTC_Raw!$A:$A),"") -> 46175 | C5: =IF(B5<>"","PASS","REVIEW") -> PASS | D5: Weekly after CFTC release | E5: CFTC_Raw | F5: Positioning feed not updated | G5: Run refreshCFTC() | H5: System
A6: Signal Engine | B6: =IFERROR(MAX(Signal_Engine!$AE:$AE),"") -> 46182.829 | C6: =IF(COUNTA(Signal_Engine!$A$2:$A$6)>0,"PASS","REVIEW") -> PASS | D6: After feed refresh | E6: Signal_Engine | F6: Machine scores not calculating | G6: Inspect Signal_Engine formula errors | H6: System
A7: Dashboard | B7: =IFERROR(Dashboard!B15,"") -> Neutral / Mixed | C7: =IF(B7<>"","PASS","REVIEW") -> PASS | D7: Live after Signal_Engine update | E7: Dashboard | F7: Front read blank | G7: Check Dashboard links | H7: System
A8: Timing Layer | B8: =IFERROR(MAX(Timing!$K:$K),"") -> 0 | C8: =IF(B8<>"","PASS","REVIEW") -> PASS | D8: Static until recalibrated | E8: Timing | F8: Timing calibration missing | G8: Re-run hourly calibration | H8: Research
A9: Seasonality Layer | B9: =IFERROR(MAX(Seasonality!$J:$J),"") -> 0 | C9: =IF(B9<>"","PASS","REVIEW") -> PASS | D9: Static until recalibrated | E9: Seasonality | F9: Seasonality missing | G9: Re-run monthly/seasonal calibration | H9: Research
A10: Briefing Front Page | B10: =NOW() -> 46182.829 | C10: =IF(Briefing!B6<>"","PASS","REVIEW") -> PASS | D10: Every open / recalculation | E10: Briefing | F10: No briefing output | G10: Check selected asset | H10: System
A11: AI Prompt Builder | B11: =NOW() -> 46182.829 | C11: =IF(AI_Prompt_Builder!A1<>"","READY","REVIEW") -> READY | D11: On demand | E11: AI_Prompt_Builder | F11: Prompt missing | G11: Review prompt template | H11: Optional

Sheet Alert_Rules
A1: MARKET MACHINE ALERT RULES — CALENDAR / BRIEFING LAYER
A3: Alert Name | B3: Asset | C3: Machine State | D3: Timing Window | E3: Trigger Logic | F3: Priority | G3: Briefing Text | H3: Delivery Channel | I3: Active | J3: Notes
A4: Morning Weather Briefing | B4: ALL | C4: Any | D4: 07:30 ET | E4: Daily health check + top machine reads | F4: Normal | G4: Morning Market Machine briefing ready. | H4: Email / Calendar / App | I4: Yes | J4: Foundation briefing.
A5: Early-Week Bearish High Watch | B5: XAGUSD | C5: Bearish | D5: Monday–Tuesday 08:30–10:30 ET | E5: Machine bearish + timing bearish high window | F5: High | G5: Bearish high-window active. Watch fake reclaim/rejection. | H5: Calendar / App | I5: Yes | J5: Use structure confirmation.
A6: Early-Week Bearish High Watch | B6: US30 | C6: Bearish | D6: Monday–Tuesday 08:30–10:30 ET | E6: Machine bearish + timing bearish high window | F6: High | G6: US30 bearish high-window active. Watch early-week rally failure. | H6: Calendar / App | I6: Yes | J6: Use structure confirmation.
A7: Bullish Weekly Low Watch | B7: XAGUSD | C7: Bullish | D7: Sunday evening / Monday morning | E7: Machine bullish + low-window alignment | F7: High | G7: Bullish low-window active. Watch early dip/support response. | H7: Calendar / App | I7: Yes | J7: Do not chase if gap stretches.
A8: Friday Terminal Extreme | B8: ALL | C8: Bullish/Bearish | D8: Friday 09:00–15:30 ET | E8: Trend week + timing terminal extreme | F8: Medium | G8: Friday terminal window. Manage continuation/reversal risk. | H8: Calendar / App | I8: Yes | J8: Pair with weekly sequence.
A9: Machine Conflict Watch | B9: ALL | C9: Mixed | D9: Any | E9: Bull and bear points within 15 points | F9: Low | G9: Mixed machine; wait for cleaner alignment. | H9: Dashboard only | I9: Yes | J9: Avoid forced thesis.
A10: Urgent Conviction Shift | B10: ALL | C10: Any | D10: Any | E10: Final machine reading changes by 2 tiers or conviction > 75/100 | F10: Urgent | G10: Machine conviction shift detected. Review dashboard immediately. | H10: App / Email | I10: Future | J10: Requires log comparison.
A11: CFTC Release Refresh | B11: ALL | C11: Any | D11: Friday evening / Saturday | E11: CFTC new report expected | F11: Normal | G11: Refresh CFTC and review positioning changes. | H11: Calendar | I11: Yes | J11: Weekly maintenance.

Sheet Notification_Log
A1: NOTIFICATION / BRIEFING LOG
A3: Timestamp | B3: Asset | C3: Machine Reading | D3: Conviction | E3: Alert Type | F3: Message | G3: Delivery Status | H3: Notes
A4: 46182.807 | B4: XAGUSD | C4: Sample | D4: — | E4: System | F4: Future notifications will append here from Apps Script. | G4: Template | H4: Do not delete headers.

Sheet AI_Control
A1: OPTIONAL AI BRIEFING CONTROL — HUMAN-REVIEWED LAYER
A3: Setting | B3: Value | C3: Status | D3: Notes | E3: Security | F3: Use
A4: AI Mode | B4: Manual Copy-Paste | C4: READY | D4: Use AI_Prompt_Builder text manually until API key/Cloud setup is desired. | E4: No key stored in sheet by default. | F4: Safest / free
A5: API Key | C5: OFF | D5: Do not store sensitive keys in shared sheets. If used later, use Apps Script PropertiesService. | E5: Sensitive | F5: Optional future
A6: Model | B6: gpt-5.5-thinking / configurable | C6: INFO | D6: For future API integration only; sheet works without AI API. | E6: N/A | F6: Future
A7: Cost Guardrail | B7: Daily briefing only | C7: INFO | D7: Avoid constant API calls; use deterministic formulas first, AI second. | E7: N/A | F7: Recommended
A8: AI Role | B8: Market Weather Briefing Editor | C8: INFO | D8: AI should summarize machine evidence, not invent signals. | E8: N/A | F8: Companion, not ruler
A9: Output Type | B9: Briefing + conflict + watch window | C9: READY | D9: AI output should mirror Briefing sheet, with stronger language and concise reasoning. | E9: N/A | F9: Future

Sheet AI_Prompt_Builder
A1: AI PROMPT BUILDER — COPY THIS INTO CHATGPT OR FUTURE API CALL
A3: Selected Asset | B3: =Briefing!B4 -> XAGUSD
A5: Generated Machine Briefing Prompt
A6: ="Act as my Market Machine briefing editor. Use only the machine evidence below. Do not invent a trade signal. Give me a concise market-weather briefing with: current environment, primary conflict, timing window, seasonality, risk notes, and what to watch n"&"ext."&CHAR(10)&CHAR(10)&Briefing!G16 -> Act as my Market Machine briefing editor. Use only the machine evidence below. Do not invent a trade signal. Give me a concise market-weather briefing with: current environment, primary conflict, timing window, seasonality, risk notes, and what to watch next. MARKET MACHINE BRIEFING — XAGUSD Environment: Neutral / Mixed | Conviction: 6/100 | Alignment: 49% Primary conflict: Mixed crosscurrents / no dominant conflict Window: Weekly High: Friday (35.8%) | Sun–Tue high 35.8% | Weekly Low: Sunday (20.7%) | Sun–Tue low 52.5% | Primary: High 09:00 ET (15.1%) / Low 18:00 ET (18.4%) Note: Mixed machine; wait for cleaner alignment. Baseline mixed-machine timing. Use as reference only; high-before-low 44.7%.
A22: Future API Note: Apps Script can call an AI API later, but this version keeps AI as an optional human-reviewed layer.

Sheet Economic_Calendar
A1: ECONOMIC CALENDAR — MANUAL / FUTURE FEED LAYER
A3: Date | B3: Time ET | C3: Event | D3: Currency/Market | E3: Expected Impact | F3: Actual | G3: Machine Interpretation | H3: Notes
C4: CPI / PCE / FOMC / NFP | D4: USD / Indices / Metals | E4: High | G4: Use to override or caution machine read around releases. | H4: Manual until reliable feed connected.
C5: Treasury auction / Fed speakers | D5: Yields | E5: Medium | G5: Watch real-yield and DXY response.
C6: CFTC Release | D6: Futures | E6: Weekly | G6: Run refreshCFTC after release. | H6: Friday/Saturday maintenance.

Sheet App_Roadmap
A1: APP ROADMAP — FROM SHEETS ENGINE TO BRIEFING APP
A3: Tier | B3: Objective | C3: Current Status | D3: Next Implementation | E3: Data Needed | F3: Output | G3: Risk | H3: Priority
A4: Tier 1 | B4: Finish calibration datasets | C4: Mostly complete | D4: Add more hourly/monthly history over time | E4: US30/SPX/NAS/VIX/XAG/SI/GC | F4: Timing + seasonality constants | G4: Small sample bias | H4: High
A5: Tier 2 | B5: Advanced timing tables | C5: Added baseline | D5: Add conditional timing by machine state + volatility regime | E5: More periods + VIX regimes | F5: Best hour/day/window by condition | G5: Overfitting | H5: High
A6: Tier 3 | B6: Machine health panel | C6: Added | D6: Surface feed state in app front page | E6: None | F6: PASS/REVIEW status | G6: False confidence if stale | H6: High
A7: Tier 4 | B7: Conviction scoring | C7: Added | D7: Track actual outcomes after each briefing | E7: Forward test log | F7: Conviction calibration curve | G7: Unvalidated scores | H7: High
A8: Tier 5 | B8: AI briefing editor | C8: Manual-ready | D8: Use prompt builder; API optional later | E8: AI API key only if desired | F8: Human-readable briefing | G8: Cost/key/security | H8: Medium
A9: Tier 6 | B9: Automated wake-up briefing | C9: Scaffolded | D9: Apps Script triggers + email/calendar/app notification | E9: Stable master sheet | F9: Morning/urgent machine briefings | G9: Notification fatigue | H9: Medium
A10: Tier 7 | B10: Streamlit/web app face | C10: Future | D10: Read Google Sheet as database, display Liner-style app UI | E10: Google Sheets API/CSV endpoint | F10: Mobile-friendly briefing app | G10: Auth/deployment | H10: Medium
